{
  "a_comp_cor_00": {
    "CumulativeVarianceExplained": 0.1267132439,
    "Mask": "combined",
    "Method": "aCompCor",
    "Retained": true,
    "SingularValue": 229.409732312,
    "VarianceExplained": 0.1267132439
  },
  "a_comp_cor_01": {
    "CumulativeVarianceExplained": 0.181406514,
    "Mask": "combined",
    "Method": "aCompCor",
    "Retained": true,
    "SingularValue": 150.7189219578,
    "VarianceExplained": 0.0546932701
  },
  "a_comp_cor_02": {
    "CumulativeVarianceExplained": 0.2273132531,
    "Mask": "combined",
    "Method": "aCompCor",
    "Retained": true,
    "SingularValue": 138.0826318429,
    "VarianceExplained": 0.0459067391
  },
  "a_comp_cor_03": {
    "CumulativeVarianceExplained": 0.2662357505,
    "Mask": "combined",
    "Method": "aCompCor",
    "Retained": true,
    "SingularValue": 127.1455551346,
    "VarianceExplained": 0.0389224973
  },
  "a_comp_cor_04": {
    "CumulativeVarianceExplained": 0.2950228271,
    "Mask": "combined",
    "Method": "aCompCor",
    "Retained": true,
    "SingularValue": 109.3451729827,
    "VarianceExplained": 0.0287870767
  },
  "a_comp_cor_05": {
    "CumulativeVarianceExplained": 0.3154524085,
    "Mask": "combined",
    "Method": "aCompCor",
    "Retained": true,
    "SingularValue": 92.1150446992,
    "VarianceExplained": 0.0204295814
  },
  "a_comp_cor_06": {
    "CumulativeVarianceExplained": 0.3328001207,
    "Mask": "combined",
    "Method": "aCompCor",
    "Retained": true,
    "SingularValue": 84.8832379457,
    "VarianceExplained": 0.0173477122
  },
  "a_comp_cor_07": {
    "CumulativeVarianceExplained": 0.3479543509,
    "Mask": "combined",
    "Method": "aCompCor",
    "Retained": true,
    "SingularValue": 79.3355386386,
    "VarianceExplained": 0.0151542303
  },
  "a_comp_cor_08": {
    "CumulativeVarianceExplained": 0.3612940781,
    "Mask": "combined",
    "Method": "aCompCor",
    "Retained": true,
    "SingularValue": 74.4345054027,
    "VarianceExplained": 0.0133397271
  },
  "a_comp_cor_09": {
    "CumulativeVarianceExplained": 0.3730027438,
    "Mask": "combined",
    "Method": "aCompCor",
    "Retained": true,
    "SingularValue": 69.735599271,
    "VarianceExplained": 0.0117086657
  },
  "a_comp_cor_10": {
    "CumulativeVarianceExplained": 0.3844770833,
    "Mask": "combined",
    "Method": "aCompCor",
    "Retained": true,
    "SingularValue": 69.0342610942,
    "VarianceExplained": 0.0114743395
  },
  "a_comp_cor_11": {
    "CumulativeVarianceExplained": 0.3950015467,
    "Mask": "combined",
    "Method": "aCompCor",
    "Retained": true,
    "SingularValue": 66.1151238374,
    "VarianceExplained": 0.0105244634
  },
  "a_comp_cor_12": {
    "CumulativeVarianceExplained": 0.4048397739,
    "Mask": "combined",
    "Method": "aCompCor",
    "Retained": true,
    "SingularValue": 63.9233103277,
    "VarianceExplained": 0.0098382272
  },
  "a_comp_cor_13": {
    "CumulativeVarianceExplained": 0.4136230661,
    "Mask": "combined",
    "Method": "aCompCor",
    "Retained": true,
    "SingularValue": 60.3989651958,
    "VarianceExplained": 0.0087832922
  },
  "a_comp_cor_14": {
    "CumulativeVarianceExplained": 0.4215746459,
    "Mask": "combined",
    "Method": "aCompCor",
    "Retained": true,
    "SingularValue": 57.4681933247,
    "VarianceExplained": 0.0079515798
  },
  "a_comp_cor_15": {
    "CumulativeVarianceExplained": 0.4286198626,
    "Mask": "combined",
    "Method": "aCompCor",
    "Retained": true,
    "SingularValue": 54.0938651659,
    "VarianceExplained": 0.0070452168
  },
  "a_comp_cor_16": {
    "CumulativeVarianceExplained": 0.4350997281,
    "Mask": "combined",
    "Method": "aCompCor",
    "Retained": true,
    "SingularValue": 51.8780720596,
    "VarianceExplained": 0.0064798655
  },
  "a_comp_cor_17": {
    "CumulativeVarianceExplained": 0.4412179789,
    "Mask": "combined",
    "Method": "aCompCor",
    "Retained": true,
    "SingularValue": 50.4097417885,
    "VarianceExplained": 0.0061182508
  },
  "a_comp_cor_18": {
    "CumulativeVarianceExplained": 0.4471419008,
    "Mask": "combined",
    "Method": "aCompCor",
    "Retained": true,
    "SingularValue": 49.6027204611,
    "VarianceExplained": 0.0059239219
  },
  "a_comp_cor_19": {
    "CumulativeVarianceExplained": 0.4526389333,
    "Mask": "combined",
    "Method": "aCompCor",
    "Retained": true,
    "SingularValue": 47.7820725343,
    "VarianceExplained": 0.0054970324
  },
  "a_comp_cor_20": {
    "CumulativeVarianceExplained": 0.4579661384,
    "Mask": "combined",
    "Method": "aCompCor",
    "Retained": true,
    "SingularValue": 47.0381834963,
    "VarianceExplained": 0.0053272051
  },
  "a_comp_cor_21": {
    "CumulativeVarianceExplained": 0.4631464948,
    "Mask": "combined",
    "Method": "aCompCor",
    "Retained": true,
    "SingularValue": 46.3853303112,
    "VarianceExplained": 0.0051803564
  },
  "a_comp_cor_22": {
    "CumulativeVarianceExplained": 0.4681178035,
    "Mask": "combined",
    "Method": "aCompCor",
    "Retained": true,
    "SingularValue": 45.4397782138,
    "VarianceExplained": 0.0049713088
  },
  "a_comp_cor_23": {
    "CumulativeVarianceExplained": 0.4730005504,
    "Mask": "combined",
    "Method": "aCompCor",
    "Retained": true,
    "SingularValue": 45.0332134,
    "VarianceExplained": 0.0048827468
  },
  "a_comp_cor_24": {
    "CumulativeVarianceExplained": 0.4777626773,
    "Mask": "combined",
    "Method": "aCompCor",
    "Retained": true,
    "SingularValue": 44.4735006925,
    "VarianceExplained": 0.0047621269
  },
  "a_comp_cor_25": {
    "CumulativeVarianceExplained": 0.4824198541,
    "Mask": "combined",
    "Method": "aCompCor",
    "Retained": true,
    "SingularValue": 43.98070611,
    "VarianceExplained": 0.0046571768
  },
  "a_comp_cor_26": {
    "CumulativeVarianceExplained": 0.4870287403,
    "Mask": "combined",
    "Method": "aCompCor",
    "Retained": true,
    "SingularValue": 43.7520922003,
    "VarianceExplained": 0.0046088862
  },
  "a_comp_cor_27": {
    "CumulativeVarianceExplained": 0.4915616319,
    "Mask": "combined",
    "Method": "aCompCor",
    "Retained": true,
    "SingularValue": 43.3898848544,
    "VarianceExplained": 0.0045328915
  },
  "a_comp_cor_28": {
    "CumulativeVarianceExplained": 0.4960675243,
    "Mask": "combined",
    "Method": "aCompCor",
    "Retained": true,
    "SingularValue": 43.2604709711,
    "VarianceExplained": 0.0045058924
  },
  "a_comp_cor_29": {
    "CumulativeVarianceExplained": 0.5004139483,
    "Mask": "combined",
    "Method": "aCompCor",
    "Retained": true,
    "SingularValue": 42.4880580316,
    "VarianceExplained": 0.0043464241
  },
  "c_comp_cor_00": {
    "CumulativeVarianceExplained": 0.1856855933,
    "Mask": "CSF",
    "Method": "aCompCor",
    "Retained": true,
    "SingularValue": 104.3982834309,
    "VarianceExplained": 0.1856855933
  },
  "c_comp_cor_01": {
    "CumulativeVarianceExplained": 0.3325336205,
    "Mask": "CSF",
    "Method": "aCompCor",
    "Retained": true,
    "SingularValue": 92.8406796906,
    "VarianceExplained": 0.1468480272
  },
  "c_comp_cor_02": {
    "CumulativeVarianceExplained": 0.4071846818,
    "Mask": "CSF",
    "Method": "aCompCor",
    "Retained": true,
    "SingularValue": 66.19455186,
    "VarianceExplained": 0.0746510613
  },
  "c_comp_cor_03": {
    "CumulativeVarianceExplained": 0.479361853,
    "Mask": "CSF",
    "Method": "aCompCor",
    "Retained": true,
    "SingularValue": 65.0884877793,
    "VarianceExplained": 0.0721771712
  },
  "c_comp_cor_04": {
    "CumulativeVarianceExplained": 0.5365794466,
    "Mask": "CSF",
    "Method": "aCompCor",
    "Retained": true,
    "SingularValue": 57.9520825622,
    "VarianceExplained": 0.0572175936
  },
  "dropped_0": {
    "CumulativeVarianceExplained": 0.6550065874,
    "Mask": "Edge",
    "Method": "EdgeRegressor",
    "Retained": false,
    "SingularValue": 96.38625907,
    "VarianceExplained": 0.0037960417
  },
  "dropped_1": {
    "CumulativeVarianceExplained": 0.6587108655,
    "Mask": "Edge",
    "Method": "EdgeRegressor",
    "Retained": false,
    "SingularValue": 95.2141365697,
    "VarianceExplained": 0.0037042781
  },
  "dropped_10": {
    "CumulativeVarianceExplained": 0.6865463629,
    "Mask": "Edge",
    "Method": "EdgeRegressor",
    "Retained": false,
    "SingularValue": 80.8464835691,
    "VarianceExplained": 0.002670687
  },
  "dropped_100": {
    "CumulativeVarianceExplained": 0.8304762958,
    "Mask": "Edge",
    "Method": "EdgeRegressor",
    "Retained": false,
    "SingularValue": 55.1211425061,
    "VarianceExplained": 0.0012414726
  },
  "dropped_101": {
    "CumulativeVarianceExplained": 0.8317122323,
    "Mask": "Edge",
    "Method": "EdgeRegressor",
    "Retained": false,
    "SingularValue": 54.9981061188,
    "VarianceExplained": 0.0012359366
  },
  "dropped_102": {
    "CumulativeVarianceExplained": 0.8329400231,
    "Mask": "Edge",
    "Method": "EdgeRegressor",
    "Retained": false,
    "SingularValue": 54.8165656751,
    "VarianceExplained": 0.0012277908
  },
  "dropped_103": {
    "CumulativeVarianceExplained": 0.8341632497,
    "Mask": "Edge",
    "Method": "EdgeRegressor",
    "Retained": false,
    "SingularValue": 54.7145830162,
    "VarianceExplained": 0.0012232266
  },
  "dropped_104": {
    "CumulativeVarianceExplained": 0.8353851663,
    "Mask": "Edge",
    "Method": "EdgeRegressor",
    "Retained": false,
    "SingularValue": 54.685277581,
    "VarianceExplained": 0.0012219166
  },
  "dropped_105": {
    "CumulativeVarianceExplained": 0.8366035818,
    "Mask": "Edge",
    "Method": "EdgeRegressor",
    "Retained": false,
    "SingularValue": 54.6068780897,
    "VarianceExplained": 0.0012184155
  },
  "dropped_106": {
    "CumulativeVarianceExplained": 0.8378179827,
    "Mask": "Edge",
    "Method": "EdgeRegressor",
    "Retained": false,
    "SingularValue": 54.5168389529,
    "VarianceExplained": 0.0012144008
  },
  "dropped_107": {
    "CumulativeVarianceExplained": 0.8390277668,
    "Mask": "Edge",
    "Method": "EdgeRegressor",
    "Retained": false,
    "SingularValue": 54.4131153578,
    "VarianceExplained": 0.0012097842
  },
  "dropped_108": {
    "CumulativeVarianceExplained": 0.8402344758,
    "Mask": "Edge",
    "Method": "EdgeRegressor",
    "Retained": false,
    "SingularValue": 54.343913005,
    "VarianceExplained": 0.001206709
  },
  "dropped_109": {
    "CumulativeVarianceExplained": 0.8414400029,
    "Mask": "Edge",
    "Method": "EdgeRegressor",
    "Retained": false,
    "SingularValue": 54.317293702,
    "VarianceExplained": 0.0012055271
  },
  "dropped_11": {
    "CumulativeVarianceExplained": 0.6891475521,
    "Mask": "Edge",
    "Method": "EdgeRegressor",
    "Retained": false,
    "SingularValue": 79.7876371797,
    "VarianceExplained": 0.0026011891
  },
  "dropped_110": {
    "CumulativeVarianceExplained": 0.8426397303,
    "Mask": "Edge",
    "Method": "EdgeRegressor",
    "Retained": false,
    "SingularValue": 54.1864780518,
    "VarianceExplained": 0.0011997274
  },
  "dropped_111": {
    "CumulativeVarianceExplained": 0.8438357497,
    "Mask": "Edge",
    "Method": "EdgeRegressor",
    "Retained": false,
    "SingularValue": 54.102676731,
    "VarianceExplained": 0.0011960194
  },
  "dropped_112": {
    "CumulativeVarianceExplained": 0.8450285724,
    "Mask": "Edge",
    "Method": "EdgeRegressor",
    "Retained": false,
    "SingularValue": 54.0303258932,
    "VarianceExplained": 0.0011928227
  },
  "dropped_113": {
    "CumulativeVarianceExplained": 0.8462161869,
    "Mask": "Edge",
    "Method": "EdgeRegressor",
    "Retained": false,
    "SingularValue": 53.9122423961,
    "VarianceExplained": 0.0011876146
  },
  "dropped_114": {
    "CumulativeVarianceExplained": 0.847398932,
    "Mask": "Edge",
    "Method": "EdgeRegressor",
    "Retained": false,
    "SingularValue": 53.8016027865,
    "VarianceExplained": 0.0011827451
  },
  "dropped_115": {
    "CumulativeVarianceExplained": 0.8485799423,
    "Mask": "Edge",
    "Method": "EdgeRegressor",
    "Retained": false,
    "SingularValue": 53.7621303267,
    "VarianceExplained": 0.0011810102
  },
  "dropped_116": {
    "CumulativeVarianceExplained": 0.849757458,
    "Mask": "Edge",
    "Method": "EdgeRegressor",
    "Retained": false,
    "SingularValue": 53.6825339534,
    "VarianceExplained": 0.0011775158
  },
  "dropped_117": {
    "CumulativeVarianceExplained": 0.8509294746,
    "Mask": "Edge",
    "Method": "EdgeRegressor",
    "Retained": false,
    "SingularValue": 53.5570330703,
    "VarianceExplained": 0.0011720165
  },
  "dropped_118": {
    "CumulativeVarianceExplained": 0.8520964663,
    "Mask": "Edge",
    "Method": "EdgeRegressor",
    "Retained": false,
    "SingularValue": 53.442100536,
    "VarianceExplained": 0.0011669917
  },
  "dropped_119": {
    "CumulativeVarianceExplained": 0.8532602022,
    "Mask": "Edge",
    "Method": "EdgeRegressor",
    "Retained": false,
    "SingularValue": 53.3674993981,
    "VarianceExplained": 0.0011637359
  },
  "dropped_12": {
    "CumulativeVarianceExplained": 0.6916586279,
    "Mask": "Edge",
    "Method": "EdgeRegressor",
    "Retained": false,
    "SingularValue": 78.3934095529,
    "VarianceExplained": 0.0025110758
  },
  "dropped_120": {
    "CumulativeVarianceExplained": 0.8544178609,
    "Mask": "Edge",
    "Method": "EdgeRegressor",
    "Retained": false,
    "SingularValue": 53.2279708456,
    "VarianceExplained": 0.0011576587
  },
  "dropped_121": {
    "CumulativeVarianceExplained": 0.855573184,
    "Mask": "Edge",
    "Method": "EdgeRegressor",
    "Retained": false,
    "SingularValue": 53.1742499224,
    "VarianceExplained": 0.0011553231
  },
  "dropped_122": {
    "CumulativeVarianceExplained": 0.8567244046,
    "Mask": "Edge",
    "Method": "EdgeRegressor",
    "Retained": false,
    "SingularValue": 53.0797545656,
    "VarianceExplained": 0.0011512206
  },
  "dropped_123": {
    "CumulativeVarianceExplained": 0.8578713271,
    "Mask": "Edge",
    "Method": "EdgeRegressor",
    "Retained": false,
    "SingularValue": 52.9805761128,
    "VarianceExplained": 0.0011469225
  },
  "dropped_124": {
    "CumulativeVarianceExplained": 0.8590154935,
    "Mask": "Edge",
    "Method": "EdgeRegressor",
    "Retained": false,
    "SingularValue": 52.9168803553,
    "VarianceExplained": 0.0011441664
  },
  "dropped_125": {
    "CumulativeVarianceExplained": 0.8601586432,
    "Mask": "Edge",
    "Method": "EdgeRegressor",
    "Retained": false,
    "SingularValue": 52.8933643567,
    "VarianceExplained": 0.0011431497
  },
  "dropped_126": {
    "CumulativeVarianceExplained": 0.8612968061,
    "Mask": "Edge",
    "Method": "EdgeRegressor",
    "Retained": false,
    "SingularValue": 52.7778691261,
    "VarianceExplained": 0.0011381629
  },
  "dropped_127": {
    "CumulativeVarianceExplained": 0.8624340765,
    "Mask": "Edge",
    "Method": "EdgeRegressor",
    "Retained": false,
    "SingularValue": 52.7571719939,
    "VarianceExplained": 0.0011372704
  },
  "dropped_128": {
    "CumulativeVarianceExplained": 0.8635618852,
    "Mask": "Edge",
    "Method": "EdgeRegressor",
    "Retained": false,
    "SingularValue": 52.5372539242,
    "VarianceExplained": 0.0011278088
  },
  "dropped_129": {
    "CumulativeVarianceExplained": 0.8646839027,
    "Mask": "Edge",
    "Method": "EdgeRegressor",
    "Retained": false,
    "SingularValue": 52.402190252,
    "VarianceExplained": 0.0011220174
  },
  "dropped_13": {
    "CumulativeVarianceExplained": 0.6940612645,
    "Mask": "Edge",
    "Method": "EdgeRegressor",
    "Retained": false,
    "SingularValue": 76.6820440462,
    "VarianceExplained": 0.0024026366
  },
  "dropped_130": {
    "CumulativeVarianceExplained": 0.8658033003,
    "Mask": "Edge",
    "Method": "EdgeRegressor",
    "Retained": false,
    "SingularValue": 52.3409772167,
    "VarianceExplained": 0.0011193976
  },
  "dropped_131": {
    "CumulativeVarianceExplained": 0.8669179915,
    "Mask": "Edge",
    "Method": "EdgeRegressor",
    "Retained": false,
    "SingularValue": 52.2308302985,
    "VarianceExplained": 0.0011146912
  },
  "dropped_132": {
    "CumulativeVarianceExplained": 0.8680316107,
    "Mask": "Edge",
    "Method": "EdgeRegressor",
    "Retained": false,
    "SingularValue": 52.2057078856,
    "VarianceExplained": 0.0011136192
  },
  "dropped_133": {
    "CumulativeVarianceExplained": 0.8691382205,
    "Mask": "Edge",
    "Method": "EdgeRegressor",
    "Retained": false,
    "SingularValue": 52.0411516133,
    "VarianceExplained": 0.0011066098
  },
  "dropped_134": {
    "CumulativeVarianceExplained": 0.8702416152,
    "Mask": "Edge",
    "Method": "EdgeRegressor",
    "Retained": false,
    "SingularValue": 51.965497611,
    "VarianceExplained": 0.0011033947
  },
  "dropped_135": {
    "CumulativeVarianceExplained": 0.8713440507,
    "Mask": "Edge",
    "Method": "EdgeRegressor",
    "Retained": false,
    "SingularValue": 51.9429043822,
    "VarianceExplained": 0.0011024355
  },
  "dropped_136": {
    "CumulativeVarianceExplained": 0.872440522,
    "Mask": "Edge",
    "Method": "EdgeRegressor",
    "Retained": false,
    "SingularValue": 51.8022083518,
    "VarianceExplained": 0.0010964713
  },
  "dropped_137": {
    "CumulativeVarianceExplained": 0.8735347384,
    "Mask": "Edge",
    "Method": "EdgeRegressor",
    "Retained": false,
    "SingularValue": 51.7489156027,
    "VarianceExplained": 0.0010942164
  },
  "dropped_138": {
    "CumulativeVarianceExplained": 0.8746264829,
    "Mask": "Edge",
    "Method": "EdgeRegressor",
    "Retained": false,
    "SingularValue": 51.6904291187,
    "VarianceExplained": 0.0010917445
  },
  "dropped_139": {
    "CumulativeVarianceExplained": 0.8757122889,
    "Mask": "Edge",
    "Method": "EdgeRegressor",
    "Retained": false,
    "SingularValue": 51.5496534353,
    "VarianceExplained": 0.001085806
  },
  "dropped_14": {
    "CumulativeVarianceExplained": 0.6964261223,
    "Mask": "Edge",
    "Method": "EdgeRegressor",
    "Retained": false,
    "SingularValue": 76.0767854881,
    "VarianceExplained": 0.0023648578
  },
  "dropped_140": {
    "CumulativeVarianceExplained": 0.8767941597,
    "Mask": "Edge",
    "Method": "EdgeRegressor",
    "Retained": false,
    "SingularValue": 51.4561581478,
    "VarianceExplained": 0.0010818709
  },
  "dropped_141": {
    "CumulativeVarianceExplained": 0.8778729222,
    "Mask": "Edge",
    "Method": "EdgeRegressor",
    "Retained": false,
    "SingularValue": 51.3821829658,
    "VarianceExplained": 0.0010787625
  },
  "dropped_142": {
    "CumulativeVarianceExplained": 0.8789469657,
    "Mask": "Edge",
    "Method": "EdgeRegressor",
    "Retained": false,
    "SingularValue": 51.2696757697,
    "VarianceExplained": 0.0010740435
  },
  "dropped_143": {
    "CumulativeVarianceExplained": 0.8800195402,
    "Mask": "Edge",
    "Method": "EdgeRegressor",
    "Retained": false,
    "SingularValue": 51.2346032263,
    "VarianceExplained": 0.0010725745
  },
  "dropped_144": {
    "CumulativeVarianceExplained": 0.8810909026,
    "Mask": "Edge",
    "Method": "EdgeRegressor",
    "Retained": false,
    "SingularValue": 51.2056451485,
    "VarianceExplained": 0.0010713624
  },
  "dropped_145": {
    "CumulativeVarianceExplained": 0.8821571581,
    "Mask": "Edge",
    "Method": "EdgeRegressor",
    "Retained": false,
    "SingularValue": 51.0834553743,
    "VarianceExplained": 0.0010662554
  },
  "dropped_146": {
    "CumulativeVarianceExplained": 0.8832207405,
    "Mask": "Edge",
    "Method": "EdgeRegressor",
    "Retained": false,
    "SingularValue": 51.0193845988,
    "VarianceExplained": 0.0010635824
  },
  "dropped_147": {
    "CumulativeVarianceExplained": 0.884281242,
    "Mask": "Edge",
    "Method": "EdgeRegressor",
    "Retained": false,
    "SingularValue": 50.9454352639,
    "VarianceExplained": 0.0010605015
  },
  "dropped_148": {
    "CumulativeVarianceExplained": 0.8853397548,
    "Mask": "Edge",
    "Method": "EdgeRegressor",
    "Retained": false,
    "SingularValue": 50.8976466667,
    "VarianceExplained": 0.0010585128
  },
  "dropped_149": {
    "CumulativeVarianceExplained": 0.8863951664,
    "Mask": "Edge",
    "Method": "EdgeRegressor",
    "Retained": false,
    "SingularValue": 50.8230314445,
    "VarianceExplained": 0.0010554116
  },
  "dropped_15": {
    "CumulativeVarianceExplained": 0.6987092257,
    "Mask": "Edge",
    "Method": "EdgeRegressor",
    "Retained": false,
    "SingularValue": 74.7502126074,
    "VarianceExplained": 0.0022831034
  },
  "dropped_150": {
    "CumulativeVarianceExplained": 0.8874433259,
    "Mask": "Edge",
    "Method": "EdgeRegressor",
    "Retained": false,
    "SingularValue": 50.6481193019,
    "VarianceExplained": 0.0010481595
  },
  "dropped_151": {
    "CumulativeVarianceExplained": 0.8884891254,
    "Mask": "Edge",
    "Method": "EdgeRegressor",
    "Retained": false,
    "SingularValue": 50.5910683712,
    "VarianceExplained": 0.0010457995
  },
  "dropped_152": {
    "CumulativeVarianceExplained": 0.889533496,
    "Mask": "Edge",
    "Method": "EdgeRegressor",
    "Retained": false,
    "SingularValue": 50.5564963828,
    "VarianceExplained": 0.0010443707
  },
  "dropped_153": {
    "CumulativeVarianceExplained": 0.8905736142,
    "Mask": "Edge",
    "Method": "EdgeRegressor",
    "Retained": false,
    "SingularValue": 50.4534624696,
    "VarianceExplained": 0.0010401181
  },
  "dropped_154": {
    "CumulativeVarianceExplained": 0.8916078122,
    "Mask": "Edge",
    "Method": "EdgeRegressor",
    "Retained": false,
    "SingularValue": 50.3096732487,
    "VarianceExplained": 0.0010341981
  },
  "dropped_155": {
    "CumulativeVarianceExplained": 0.8926394445,
    "Mask": "Edge",
    "Method": "EdgeRegressor",
    "Retained": false,
    "SingularValue": 50.24722731,
    "VarianceExplained": 0.0010316323
  },
  "dropped_156": {
    "CumulativeVarianceExplained": 0.8936669557,
    "Mask": "Edge",
    "Method": "EdgeRegressor",
    "Retained": false,
    "SingularValue": 50.1467641312,
    "VarianceExplained": 0.0010275112
  },
  "dropped_157": {
    "CumulativeVarianceExplained": 0.8946909918,
    "Mask": "Edge",
    "Method": "EdgeRegressor",
    "Retained": false,
    "SingularValue": 50.0618952762,
    "VarianceExplained": 0.0010240362
  },
  "dropped_158": {
    "CumulativeVarianceExplained": 0.8957100911,
    "Mask": "Edge",
    "Method": "EdgeRegressor",
    "Retained": false,
    "SingularValue": 49.9410750499,
    "VarianceExplained": 0.0010190993
  },
  "dropped_159": {
    "CumulativeVarianceExplained": 0.8967270275,
    "Mask": "Edge",
    "Method": "EdgeRegressor",
    "Retained": false,
    "SingularValue": 49.888050969,
    "VarianceExplained": 0.0010169364
  },
  "dropped_16": {
    "CumulativeVarianceExplained": 0.7009703589,
    "Mask": "Edge",
    "Method": "EdgeRegressor",
    "Retained": false,
    "SingularValue": 74.3896830757,
    "VarianceExplained": 0.0022611332
  },
  "dropped_160": {
    "CumulativeVarianceExplained": 0.8977416913,
    "Mask": "Edge",
    "Method": "EdgeRegressor",
    "Retained": false,
    "SingularValue": 49.8322749321,
    "VarianceExplained": 0.0010146638
  },
  "dropped_161": {
    "CumulativeVarianceExplained": 0.8987535308,
    "Mask": "Edge",
    "Method": "EdgeRegressor",
    "Retained": false,
    "SingularValue": 49.7628737615,
    "VarianceExplained": 0.0010118395
  },
  "dropped_162": {
    "CumulativeVarianceExplained": 0.8997619003,
    "Mask": "Edge",
    "Method": "EdgeRegressor",
    "Retained": false,
    "SingularValue": 49.6774715126,
    "VarianceExplained": 0.0010083695
  },
  "dropped_163": {
    "CumulativeVarianceExplained": 0.900765959,
    "Mask": "Edge",
    "Method": "EdgeRegressor",
    "Retained": false,
    "SingularValue": 49.5711733623,
    "VarianceExplained": 0.0010040587
  },
  "dropped_164": {
    "CumulativeVarianceExplained": 0.9017659338,
    "Mask": "Edge",
    "Method": "EdgeRegressor",
    "Retained": false,
    "SingularValue": 49.4702560228,
    "VarianceExplained": 0.0009999748
  },
  "dropped_165": {
    "CumulativeVarianceExplained": 0.902762188,
    "Mask": "Edge",
    "Method": "EdgeRegressor",
    "Retained": false,
    "SingularValue": 49.3781393057,
    "VarianceExplained": 0.0009962542
  },
  "dropped_166": {
    "CumulativeVarianceExplained": 0.9037565153,
    "Mask": "Edge",
    "Method": "EdgeRegressor",
    "Retained": false,
    "SingularValue": 49.3303646026,
    "VarianceExplained": 0.0009943273
  },
  "dropped_167": {
    "CumulativeVarianceExplained": 0.9047467544,
    "Mask": "Edge",
    "Method": "EdgeRegressor",
    "Retained": false,
    "SingularValue": 49.2288491318,
    "VarianceExplained": 0.0009902391
  },
  "dropped_168": {
    "CumulativeVarianceExplained": 0.9057342501,
    "Mask": "Edge",
    "Method": "EdgeRegressor",
    "Retained": false,
    "SingularValue": 49.1606080058,
    "VarianceExplained": 0.0009874957
  },
  "dropped_169": {
    "CumulativeVarianceExplained": 0.906719191,
    "Mask": "Edge",
    "Method": "EdgeRegressor",
    "Retained": false,
    "SingularValue": 49.0969728192,
    "VarianceExplained": 0.0009849409
  },
  "dropped_17": {
    "CumulativeVarianceExplained": 0.7031927658,
    "Mask": "Edge",
    "Method": "EdgeRegressor",
    "Retained": false,
    "SingularValue": 73.7498994235,
    "VarianceExplained": 0.002222407
  },
  "dropped_170": {
    "CumulativeVarianceExplained": 0.9076998684,
    "Mask": "Edge",
    "Method": "EdgeRegressor",
    "Retained": false,
    "SingularValue": 48.990595804,
    "VarianceExplained": 0.0009806774
  },
  "dropped_171": {
    "CumulativeVarianceExplained": 0.9086786527,
    "Mask": "Edge",
    "Method": "EdgeRegressor",
    "Retained": false,
    "SingularValue": 48.9432875603,
    "VarianceExplained": 0.0009787843
  },
  "dropped_172": {
    "CumulativeVarianceExplained": 0.909655594,
    "Mask": "Edge",
    "Method": "EdgeRegressor",
    "Retained": false,
    "SingularValue": 48.8971875198,
    "VarianceExplained": 0.0009769413
  },
  "dropped_173": {
    "CumulativeVarianceExplained": 0.9106308223,
    "Mask": "Edge",
    "Method": "EdgeRegressor",
    "Retained": false,
    "SingularValue": 48.8542979097,
    "VarianceExplained": 0.0009752283
  },
  "dropped_174": {
    "CumulativeVarianceExplained": 0.911601132,
    "Mask": "Edge",
    "Method": "EdgeRegressor",
    "Retained": false,
    "SingularValue": 48.7309435879,
    "VarianceExplained": 0.0009703097
  },
  "dropped_175": {
    "CumulativeVarianceExplained": 0.9125691192,
    "Mask": "Edge",
    "Method": "EdgeRegressor",
    "Retained": false,
    "SingularValue": 48.6725895975,
    "VarianceExplained": 0.0009679872
  },
  "dropped_176": {
    "CumulativeVarianceExplained": 0.9135328079,
    "Mask": "Edge",
    "Method": "EdgeRegressor",
    "Retained": false,
    "SingularValue": 48.5643995034,
    "VarianceExplained": 0.0009636887
  },
  "dropped_177": {
    "CumulativeVarianceExplained": 0.9144931762,
    "Mask": "Edge",
    "Method": "EdgeRegressor",
    "Retained": false,
    "SingularValue": 48.4806632269,
    "VarianceExplained": 0.0009603683
  },
  "dropped_178": {
    "CumulativeVarianceExplained": 0.9154497839,
    "Mask": "Edge",
    "Method": "EdgeRegressor",
    "Retained": false,
    "SingularValue": 48.385648979,
    "VarianceExplained": 0.0009566077
  },
  "dropped_179": {
    "CumulativeVarianceExplained": 0.9164042045,
    "Mask": "Edge",
    "Method": "EdgeRegressor",
    "Retained": false,
    "SingularValue": 48.3303048482,
    "VarianceExplained": 0.0009544206
  },
  "dropped_18": {
    "CumulativeVarianceExplained": 0.7053578153,
    "Mask": "Edge",
    "Method": "EdgeRegressor",
    "Retained": false,
    "SingularValue": 72.7919832069,
    "VarianceExplained": 0.0021650495
  },
  "dropped_180": {
    "CumulativeVarianceExplained": 0.9173544414,
    "Mask": "Edge",
    "Method": "EdgeRegressor",
    "Retained": false,
    "SingularValue": 48.2242610878,
    "VarianceExplained": 0.0009502369
  },
  "dropped_181": {
    "CumulativeVarianceExplained": 0.9183038847,
    "Mask": "Edge",
    "Method": "EdgeRegressor",
    "Retained": false,
    "SingularValue": 48.2041193833,
    "VarianceExplained": 0.0009494433
  },
  "dropped_182": {
    "CumulativeVarianceExplained": 0.9192506,
    "Mask": "Edge",
    "Method": "EdgeRegressor",
    "Retained": false,
    "SingularValue": 48.1348199356,
    "VarianceExplained": 0.0009467154
  },
  "dropped_183": {
    "CumulativeVarianceExplained": 0.920192505,
    "Mask": "Edge",
    "Method": "EdgeRegressor",
    "Retained": false,
    "SingularValue": 48.0123753235,
    "VarianceExplained": 0.000941905
  },
  "dropped_184": {
    "CumulativeVarianceExplained": 0.9211332859,
    "Mask": "Edge",
    "Method": "EdgeRegressor",
    "Retained": false,
    "SingularValue": 47.9837149681,
    "VarianceExplained": 0.0009407808
  },
  "dropped_185": {
    "CumulativeVarianceExplained": 0.9220705262,
    "Mask": "Edge",
    "Method": "EdgeRegressor",
    "Retained": false,
    "SingularValue": 47.8933394746,
    "VarianceExplained": 0.0009372403
  },
  "dropped_186": {
    "CumulativeVarianceExplained": 0.9230017716,
    "Mask": "Edge",
    "Method": "EdgeRegressor",
    "Retained": false,
    "SingularValue": 47.7399227852,
    "VarianceExplained": 0.0009312454
  },
  "dropped_187": {
    "CumulativeVarianceExplained": 0.9239316948,
    "Mask": "Edge",
    "Method": "EdgeRegressor",
    "Retained": false,
    "SingularValue": 47.7060191235,
    "VarianceExplained": 0.0009299232
  },
  "dropped_188": {
    "CumulativeVarianceExplained": 0.9248592312,
    "Mask": "Edge",
    "Method": "EdgeRegressor",
    "Retained": false,
    "SingularValue": 47.6447586425,
    "VarianceExplained": 0.0009275364
  },
  "dropped_189": {
    "CumulativeVarianceExplained": 0.9257837848,
    "Mask": "Edge",
    "Method": "EdgeRegressor",
    "Retained": false,
    "SingularValue": 47.5680855577,
    "VarianceExplained": 0.0009245535
  },
  "dropped_19": {
    "CumulativeVarianceExplained": 0.7075180084,
    "Mask": "Edge",
    "Method": "EdgeRegressor",
    "Retained": false,
    "SingularValue": 72.7102986854,
    "VarianceExplained": 0.0021601931
  },
  "dropped_190": {
    "CumulativeVarianceExplained": 0.9267051658,
    "Mask": "Edge",
    "Method": "EdgeRegressor",
    "Retained": false,
    "SingularValue": 47.4864033915,
    "VarianceExplained": 0.0009213811
  },
  "dropped_191": {
    "CumulativeVarianceExplained": 0.92762396,
    "Mask": "Edge",
    "Method": "EdgeRegressor",
    "Retained": false,
    "SingularValue": 47.419693567,
    "VarianceExplained": 0.0009187941
  },
  "dropped_192": {
    "CumulativeVarianceExplained": 0.9285395808,
    "Mask": "Edge",
    "Method": "EdgeRegressor",
    "Retained": false,
    "SingularValue": 47.3377343228,
    "VarianceExplained": 0.0009156208
  },
  "dropped_193": {
    "CumulativeVarianceExplained": 0.9294525835,
    "Mask": "Edge",
    "Method": "EdgeRegressor",
    "Retained": false,
    "SingularValue": 47.2700067839,
    "VarianceExplained": 0.0009130027
  },
  "dropped_194": {
    "CumulativeVarianceExplained": 0.9303624679,
    "Mask": "Edge",
    "Method": "EdgeRegressor",
    "Retained": false,
    "SingularValue": 47.1892150163,
    "VarianceExplained": 0.0009098844
  },
  "dropped_195": {
    "CumulativeVarianceExplained": 0.9312685956,
    "Mask": "Edge",
    "Method": "EdgeRegressor",
    "Retained": false,
    "SingularValue": 47.091697643,
    "VarianceExplained": 0.0009061277
  },
  "dropped_196": {
    "CumulativeVarianceExplained": 0.9321721449,
    "Mask": "Edge",
    "Method": "EdgeRegressor",
    "Retained": false,
    "SingularValue": 47.0246483334,
    "VarianceExplained": 0.0009035493
  },
  "dropped_197": {
    "CumulativeVarianceExplained": 0.9330698763,
    "Mask": "Edge",
    "Method": "EdgeRegressor",
    "Retained": false,
    "SingularValue": 46.8730115921,
    "VarianceExplained": 0.0008977314
  },
  "dropped_198": {
    "CumulativeVarianceExplained": 0.933964655,
    "Mask": "Edge",
    "Method": "EdgeRegressor",
    "Retained": false,
    "SingularValue": 46.7958611918,
    "VarianceExplained": 0.0008947786
  },
  "dropped_199": {
    "CumulativeVarianceExplained": 0.934857646,
    "Mask": "Edge",
    "Method": "EdgeRegressor",
    "Retained": false,
    "SingularValue": 46.7490942202,
    "VarianceExplained": 0.0008929911
  },
  "dropped_2": {
    "CumulativeVarianceExplained": 0.6623538011,
    "Mask": "Edge",
    "Method": "EdgeRegressor",
    "Retained": false,
    "SingularValue": 94.4224759539,
    "VarianceExplained": 0.0036429356
  },
  "dropped_20": {
    "CumulativeVarianceExplained": 0.7096366318,
    "Mask": "Edge",
    "Method": "EdgeRegressor",
    "Retained": false,
    "SingularValue": 72.0072976148,
    "VarianceExplained": 0.0021186233
  },
  "dropped_200": {
    "CumulativeVarianceExplained": 0.9357445424,
    "Mask": "Edge",
    "Method": "EdgeRegressor",
    "Retained": false,
    "SingularValue": 46.5892885941,
    "VarianceExplained": 0.0008868964
  },
  "dropped_201": {
    "CumulativeVarianceExplained": 0.936630831,
    "Mask": "Edge",
    "Method": "EdgeRegressor",
    "Retained": false,
    "SingularValue": 46.573322551,
    "VarianceExplained": 0.0008862886
  },
  "dropped_202": {
    "CumulativeVarianceExplained": 0.9375119754,
    "Mask": "Edge",
    "Method": "EdgeRegressor",
    "Retained": false,
    "SingularValue": 46.4379648201,
    "VarianceExplained": 0.0008811444
  },
  "dropped_203": {
    "CumulativeVarianceExplained": 0.9383894542,
    "Mask": "Edge",
    "Method": "EdgeRegressor",
    "Retained": false,
    "SingularValue": 46.341270942,
    "VarianceExplained": 0.0008774787
  },
  "dropped_204": {
    "CumulativeVarianceExplained": 0.9392640164,
    "Mask": "Edge",
    "Method": "EdgeRegressor",
    "Retained": false,
    "SingularValue": 46.2641946329,
    "VarianceExplained": 0.0008745623
  },
  "dropped_205": {
    "CumulativeVarianceExplained": 0.9401373428,
    "Mask": "Edge",
    "Method": "EdgeRegressor",
    "Retained": false,
    "SingularValue": 46.2314927024,
    "VarianceExplained": 0.0008733263
  },
  "dropped_206": {
    "CumulativeVarianceExplained": 0.9410057645,
    "Mask": "Edge",
    "Method": "EdgeRegressor",
    "Retained": false,
    "SingularValue": 46.1014918107,
    "VarianceExplained": 0.0008684217
  },
  "dropped_207": {
    "CumulativeVarianceExplained": 0.9418679009,
    "Mask": "Edge",
    "Method": "EdgeRegressor",
    "Retained": false,
    "SingularValue": 45.9343558305,
    "VarianceExplained": 0.0008621364
  },
  "dropped_208": {
    "CumulativeVarianceExplained": 0.9427291416,
    "Mask": "Edge",
    "Method": "EdgeRegressor",
    "Retained": false,
    "SingularValue": 45.9104884858,
    "VarianceExplained": 0.0008612407
  },
  "dropped_209": {
    "CumulativeVarianceExplained": 0.9435871674,
    "Mask": "Edge",
    "Method": "EdgeRegressor",
    "Retained": false,
    "SingularValue": 45.8247187202,
    "VarianceExplained": 0.0008580258
  },
  "dropped_21": {
    "CumulativeVarianceExplained": 0.7117007711,
    "Mask": "Edge",
    "Method": "EdgeRegressor",
    "Retained": false,
    "SingularValue": 71.0753722473,
    "VarianceExplained": 0.0020641393
  },
  "dropped_210": {
    "CumulativeVarianceExplained": 0.9444410399,
    "Mask": "Edge",
    "Method": "EdgeRegressor",
    "Retained": false,
    "SingularValue": 45.7136785167,
    "VarianceExplained": 0.0008538726
  },
  "dropped_211": {
    "CumulativeVarianceExplained": 0.9452902708,
    "Mask": "Edge",
    "Method": "EdgeRegressor",
    "Retained": false,
    "SingularValue": 45.5892582045,
    "VarianceExplained": 0.0008492309
  },
  "dropped_212": {
    "CumulativeVarianceExplained": 0.9461384798,
    "Mask": "Edge",
    "Method": "EdgeRegressor",
    "Retained": false,
    "SingularValue": 45.5618207061,
    "VarianceExplained": 0.000848209
  },
  "dropped_213": {
    "CumulativeVarianceExplained": 0.9469813898,
    "Mask": "Edge",
    "Method": "EdgeRegressor",
    "Retained": false,
    "SingularValue": 45.4192790787,
    "VarianceExplained": 0.00084291
  },
  "dropped_214": {
    "CumulativeVarianceExplained": 0.9478205808,
    "Mask": "Edge",
    "Method": "EdgeRegressor",
    "Retained": false,
    "SingularValue": 45.3189711341,
    "VarianceExplained": 0.000839191
  },
  "dropped_215": {
    "CumulativeVarianceExplained": 0.9486561427,
    "Mask": "Edge",
    "Method": "EdgeRegressor",
    "Retained": false,
    "SingularValue": 45.2208763408,
    "VarianceExplained": 0.000835562
  },
  "dropped_216": {
    "CumulativeVarianceExplained": 0.9494906661,
    "Mask": "Edge",
    "Method": "EdgeRegressor",
    "Retained": false,
    "SingularValue": 45.192762502,
    "VarianceExplained": 0.0008345234
  },
  "dropped_217": {
    "CumulativeVarianceExplained": 0.950321479,
    "Mask": "Edge",
    "Method": "EdgeRegressor",
    "Retained": false,
    "SingularValue": 45.0921808745,
    "VarianceExplained": 0.0008308128
  },
  "dropped_218": {
    "CumulativeVarianceExplained": 0.951150863,
    "Mask": "Edge",
    "Method": "EdgeRegressor",
    "Retained": false,
    "SingularValue": 45.0533915215,
    "VarianceExplained": 0.0008293841
  },
  "dropped_219": {
    "CumulativeVarianceExplained": 0.9519729883,
    "Mask": "Edge",
    "Method": "EdgeRegressor",
    "Retained": false,
    "SingularValue": 44.8558039254,
    "VarianceExplained": 0.0008221253
  },
  "dropped_22": {
    "CumulativeVarianceExplained": 0.7137164538,
    "Mask": "Edge",
    "Method": "EdgeRegressor",
    "Retained": false,
    "SingularValue": 70.236154117,
    "VarianceExplained": 0.0020156827
  },
  "dropped_220": {
    "CumulativeVarianceExplained": 0.952790006,
    "Mask": "Edge",
    "Method": "EdgeRegressor",
    "Retained": false,
    "SingularValue": 44.7162486671,
    "VarianceExplained": 0.0008170177
  },
  "dropped_221": {
    "CumulativeVarianceExplained": 0.9536040927,
    "Mask": "Edge",
    "Method": "EdgeRegressor",
    "Retained": false,
    "SingularValue": 44.6359683725,
    "VarianceExplained": 0.0008140867
  },
  "dropped_222": {
    "CumulativeVarianceExplained": 0.9544163443,
    "Mask": "Edge",
    "Method": "EdgeRegressor",
    "Retained": false,
    "SingularValue": 44.5856323461,
    "VarianceExplained": 0.0008122516
  },
  "dropped_223": {
    "CumulativeVarianceExplained": 0.9552250959,
    "Mask": "Edge",
    "Method": "EdgeRegressor",
    "Retained": false,
    "SingularValue": 44.4894688152,
    "VarianceExplained": 0.0008087516
  },
  "dropped_224": {
    "CumulativeVarianceExplained": 0.9560329039,
    "Mask": "Edge",
    "Method": "EdgeRegressor",
    "Retained": false,
    "SingularValue": 44.4635072557,
    "VarianceExplained": 0.000807808
  },
  "dropped_225": {
    "CumulativeVarianceExplained": 0.9568389523,
    "Mask": "Edge",
    "Method": "EdgeRegressor",
    "Retained": false,
    "SingularValue": 44.4150527203,
    "VarianceExplained": 0.0008060483
  },
  "dropped_226": {
    "CumulativeVarianceExplained": 0.9576416338,
    "Mask": "Edge",
    "Method": "EdgeRegressor",
    "Retained": false,
    "SingularValue": 44.3221962282,
    "VarianceExplained": 0.0008026815
  },
  "dropped_227": {
    "CumulativeVarianceExplained": 0.9584399231,
    "Mask": "Edge",
    "Method": "EdgeRegressor",
    "Retained": false,
    "SingularValue": 44.2007658977,
    "VarianceExplained": 0.0007982893
  },
  "dropped_228": {
    "CumulativeVarianceExplained": 0.9592360347,
    "Mask": "Edge",
    "Method": "EdgeRegressor",
    "Retained": false,
    "SingularValue": 44.1404343137,
    "VarianceExplained": 0.0007961116
  },
  "dropped_229": {
    "CumulativeVarianceExplained": 0.9600283077,
    "Mask": "Edge",
    "Method": "EdgeRegressor",
    "Retained": false,
    "SingularValue": 44.0338915458,
    "VarianceExplained": 0.000792273
  },
  "dropped_23": {
    "CumulativeVarianceExplained": 0.7156919157,
    "Mask": "Edge",
    "Method": "EdgeRegressor",
    "Retained": false,
    "SingularValue": 69.5318799021,
    "VarianceExplained": 0.0019754619
  },
  "dropped_230": {
    "CumulativeVarianceExplained": 0.9608190191,
    "Mask": "Edge",
    "Method": "EdgeRegressor",
    "Retained": false,
    "SingularValue": 43.990475338,
    "VarianceExplained": 0.0007907115
  },
  "dropped_231": {
    "CumulativeVarianceExplained": 0.9616075663,
    "Mask": "Edge",
    "Method": "EdgeRegressor",
    "Retained": false,
    "SingularValue": 43.9302309459,
    "VarianceExplained": 0.0007885472
  },
  "dropped_232": {
    "CumulativeVarianceExplained": 0.9623954759,
    "Mask": "Edge",
    "Method": "EdgeRegressor",
    "Retained": false,
    "SingularValue": 43.9124654415,
    "VarianceExplained": 0.0007879096
  },
  "dropped_233": {
    "CumulativeVarianceExplained": 0.963178161,
    "Mask": "Edge",
    "Method": "EdgeRegressor",
    "Retained": false,
    "SingularValue": 43.7666381903,
    "VarianceExplained": 0.0007826852
  },
  "dropped_234": {
    "CumulativeVarianceExplained": 0.9639563998,
    "Mask": "Edge",
    "Method": "EdgeRegressor",
    "Retained": false,
    "SingularValue": 43.6421429425,
    "VarianceExplained": 0.0007782388
  },
  "dropped_235": {
    "CumulativeVarianceExplained": 0.9647317841,
    "Mask": "Edge",
    "Method": "EdgeRegressor",
    "Retained": false,
    "SingularValue": 43.5620320035,
    "VarianceExplained": 0.0007753843
  },
  "dropped_236": {
    "CumulativeVarianceExplained": 0.9655024613,
    "Mask": "Edge",
    "Method": "EdgeRegressor",
    "Retained": false,
    "SingularValue": 43.4296064488,
    "VarianceExplained": 0.0007706772
  },
  "dropped_237": {
    "CumulativeVarianceExplained": 0.9662690434,
    "Mask": "Edge",
    "Method": "EdgeRegressor",
    "Retained": false,
    "SingularValue": 43.3140693891,
    "VarianceExplained": 0.0007665821
  },
  "dropped_238": {
    "CumulativeVarianceExplained": 0.9670345176,
    "Mask": "Edge",
    "Method": "EdgeRegressor",
    "Retained": false,
    "SingularValue": 43.2827568572,
    "VarianceExplained": 0.0007654742
  },
  "dropped_239": {
    "CumulativeVarianceExplained": 0.9677941819,
    "Mask": "Edge",
    "Method": "EdgeRegressor",
    "Retained": false,
    "SingularValue": 43.1181883038,
    "VarianceExplained": 0.0007596643
  },
  "dropped_24": {
    "CumulativeVarianceExplained": 0.717662997,
    "Mask": "Edge",
    "Method": "EdgeRegressor",
    "Retained": false,
    "SingularValue": 69.4547429483,
    "VarianceExplained": 0.0019710813
  },
  "dropped_240": {
    "CumulativeVarianceExplained": 0.9685480818,
    "Mask": "Edge",
    "Method": "EdgeRegressor",
    "Retained": false,
    "SingularValue": 42.9542822536,
    "VarianceExplained": 0.0007538998
  },
  "dropped_241": {
    "CumulativeVarianceExplained": 0.9692999501,
    "Mask": "Edge",
    "Method": "EdgeRegressor",
    "Retained": false,
    "SingularValue": 42.8963681489,
    "VarianceExplained": 0.0007518683
  },
  "dropped_242": {
    "CumulativeVarianceExplained": 0.9700490606,
    "Mask": "Edge",
    "Method": "EdgeRegressor",
    "Retained": false,
    "SingularValue": 42.8176263244,
    "VarianceExplained": 0.0007491105
  },
  "dropped_243": {
    "CumulativeVarianceExplained": 0.9707920656,
    "Mask": "Edge",
    "Method": "EdgeRegressor",
    "Retained": false,
    "SingularValue": 42.6427812576,
    "VarianceExplained": 0.0007430051
  },
  "dropped_244": {
    "CumulativeVarianceExplained": 0.9715336949,
    "Mask": "Edge",
    "Method": "EdgeRegressor",
    "Retained": false,
    "SingularValue": 42.6032841098,
    "VarianceExplained": 0.0007416293
  },
  "dropped_245": {
    "CumulativeVarianceExplained": 0.9722737269,
    "Mask": "Edge",
    "Method": "EdgeRegressor",
    "Retained": false,
    "SingularValue": 42.5573798098,
    "VarianceExplained": 0.000740032
  },
  "dropped_246": {
    "CumulativeVarianceExplained": 0.973010196,
    "Mask": "Edge",
    "Method": "EdgeRegressor",
    "Retained": false,
    "SingularValue": 42.4548086182,
    "VarianceExplained": 0.000736469
  },
  "dropped_247": {
    "CumulativeVarianceExplained": 0.9737438472,
    "Mask": "Edge",
    "Method": "EdgeRegressor",
    "Retained": false,
    "SingularValue": 42.3735130196,
    "VarianceExplained": 0.0007336513
  },
  "dropped_248": {
    "CumulativeVarianceExplained": 0.9744755684,
    "Mask": "Edge",
    "Method": "EdgeRegressor",
    "Retained": false,
    "SingularValue": 42.3177381991,
    "VarianceExplained": 0.0007317212
  },
  "dropped_249": {
    "CumulativeVarianceExplained": 0.9752027576,
    "Mask": "Edge",
    "Method": "EdgeRegressor",
    "Retained": false,
    "SingularValue": 42.1864864069,
    "VarianceExplained": 0.0007271892
  },
  "dropped_25": {
    "CumulativeVarianceExplained": 0.7195930797,
    "Mask": "Edge",
    "Method": "EdgeRegressor",
    "Retained": false,
    "SingularValue": 68.7286151318,
    "VarianceExplained": 0.0019300827
  },
  "dropped_250": {
    "CumulativeVarianceExplained": 0.9759277798,
    "Mask": "Edge",
    "Method": "EdgeRegressor",
    "Retained": false,
    "SingularValue": 42.1235822311,
    "VarianceExplained": 0.0007250222
  },
  "dropped_251": {
    "CumulativeVarianceExplained": 0.9766459209,
    "Mask": "Edge",
    "Method": "EdgeRegressor",
    "Retained": false,
    "SingularValue": 41.9232094277,
    "VarianceExplained": 0.0007181411
  },
  "dropped_252": {
    "CumulativeVarianceExplained": 0.97736294,
    "Mask": "Edge",
    "Method": "EdgeRegressor",
    "Retained": false,
    "SingularValue": 41.8904475466,
    "VarianceExplained": 0.0007170191
  },
  "dropped_253": {
    "CumulativeVarianceExplained": 0.9780770801,
    "Mask": "Edge",
    "Method": "EdgeRegressor",
    "Retained": false,
    "SingularValue": 41.8062628616,
    "VarianceExplained": 0.0007141401
  },
  "dropped_254": {
    "CumulativeVarianceExplained": 0.9787897936,
    "Mask": "Edge",
    "Method": "EdgeRegressor",
    "Retained": false,
    "SingularValue": 41.764486269,
    "VarianceExplained": 0.0007127135
  },
  "dropped_255": {
    "CumulativeVarianceExplained": 0.9794963115,
    "Mask": "Edge",
    "Method": "EdgeRegressor",
    "Retained": false,
    "SingularValue": 41.5825585274,
    "VarianceExplained": 0.0007065178
  },
  "dropped_256": {
    "CumulativeVarianceExplained": 0.9802023572,
    "Mask": "Edge",
    "Method": "EdgeRegressor",
    "Retained": false,
    "SingularValue": 41.5686613388,
    "VarianceExplained": 0.0007060457
  },
  "dropped_257": {
    "CumulativeVarianceExplained": 0.9809031981,
    "Mask": "Edge",
    "Method": "EdgeRegressor",
    "Retained": false,
    "SingularValue": 41.4151616876,
    "VarianceExplained": 0.0007008409
  },
  "dropped_258": {
    "CumulativeVarianceExplained": 0.9816005564,
    "Mask": "Edge",
    "Method": "EdgeRegressor",
    "Retained": false,
    "SingularValue": 41.3121340346,
    "VarianceExplained": 0.0006973583
  },
  "dropped_259": {
    "CumulativeVarianceExplained": 0.9822946653,
    "Mask": "Edge",
    "Method": "EdgeRegressor",
    "Retained": false,
    "SingularValue": 41.2157739742,
    "VarianceExplained": 0.0006941089
  },
  "dropped_26": {
    "CumulativeVarianceExplained": 0.7215059986,
    "Mask": "Edge",
    "Method": "EdgeRegressor",
    "Retained": false,
    "SingularValue": 68.4223400755,
    "VarianceExplained": 0.0019129189
  },
  "dropped_260": {
    "CumulativeVarianceExplained": 0.982985005,
    "Mask": "Edge",
    "Method": "EdgeRegressor",
    "Retained": false,
    "SingularValue": 41.1037141297,
    "VarianceExplained": 0.0006903397
  },
  "dropped_261": {
    "CumulativeVarianceExplained": 0.9836678489,
    "Mask": "Edge",
    "Method": "EdgeRegressor",
    "Retained": false,
    "SingularValue": 40.8799485152,
    "VarianceExplained": 0.0006828439
  },
  "dropped_262": {
    "CumulativeVarianceExplained": 0.98434918,
    "Mask": "Edge",
    "Method": "EdgeRegressor",
    "Retained": false,
    "SingularValue": 40.8346415233,
    "VarianceExplained": 0.0006813311
  },
  "dropped_263": {
    "CumulativeVarianceExplained": 0.9850258162,
    "Mask": "Edge",
    "Method": "EdgeRegressor",
    "Retained": false,
    "SingularValue": 40.6937064903,
    "VarianceExplained": 0.0006766362
  },
  "dropped_264": {
    "CumulativeVarianceExplained": 0.9856983032,
    "Mask": "Edge",
    "Method": "EdgeRegressor",
    "Retained": false,
    "SingularValue": 40.5687453942,
    "VarianceExplained": 0.000672487
  },
  "dropped_265": {
    "CumulativeVarianceExplained": 0.9863626065,
    "Mask": "Edge",
    "Method": "EdgeRegressor",
    "Retained": false,
    "SingularValue": 40.3211441138,
    "VarianceExplained": 0.0006643033
  },
  "dropped_266": {
    "CumulativeVarianceExplained": 0.9870253297,
    "Mask": "Edge",
    "Method": "EdgeRegressor",
    "Retained": false,
    "SingularValue": 40.2731611253,
    "VarianceExplained": 0.0006627232
  },
  "dropped_267": {
    "CumulativeVarianceExplained": 0.987684872,
    "Mask": "Edge",
    "Method": "EdgeRegressor",
    "Retained": false,
    "SingularValue": 40.176396703,
    "VarianceExplained": 0.0006595424
  },
  "dropped_268": {
    "CumulativeVarianceExplained": 0.9883407613,
    "Mask": "Edge",
    "Method": "EdgeRegressor",
    "Retained": false,
    "SingularValue": 40.064978964,
    "VarianceExplained": 0.0006558893
  },
  "dropped_269": {
    "CumulativeVarianceExplained": 0.9889948037,
    "Mask": "Edge",
    "Method": "EdgeRegressor",
    "Retained": false,
    "SingularValue": 40.0085281477,
    "VarianceExplained": 0.0006540424
  },
  "dropped_27": {
    "CumulativeVarianceExplained": 0.723399915,
    "Mask": "Edge",
    "Method": "EdgeRegressor",
    "Retained": false,
    "SingularValue": 68.0816442019,
    "VarianceExplained": 0.0018939164
  },
  "dropped_270": {
    "CumulativeVarianceExplained": 0.9896465155,
    "Mask": "Edge",
    "Method": "EdgeRegressor",
    "Retained": false,
    "SingularValue": 39.9371847387,
    "VarianceExplained": 0.0006517118
  },
  "dropped_271": {
    "CumulativeVarianceExplained": 0.9902932,
    "Mask": "Edge",
    "Method": "EdgeRegressor",
    "Retained": false,
    "SingularValue": 39.7828451009,
    "VarianceExplained": 0.0006466844
  },
  "dropped_272": {
    "CumulativeVarianceExplained": 0.9909373736,
    "Mask": "Edge",
    "Method": "EdgeRegressor",
    "Retained": false,
    "SingularValue": 39.7055416171,
    "VarianceExplained": 0.0006441737
  },
  "dropped_273": {
    "CumulativeVarianceExplained": 0.9915780563,
    "Mask": "Edge",
    "Method": "EdgeRegressor",
    "Retained": false,
    "SingularValue": 39.5978061886,
    "VarianceExplained": 0.0006406827
  },
  "dropped_274": {
    "CumulativeVarianceExplained": 0.9922108567,
    "Mask": "Edge",
    "Method": "EdgeRegressor",
    "Retained": false,
    "SingularValue": 39.353467309,
    "VarianceExplained": 0.0006328004
  },
  "dropped_275": {
    "CumulativeVarianceExplained": 0.9928425182,
    "Mask": "Edge",
    "Method": "EdgeRegressor",
    "Retained": false,
    "SingularValue": 39.3180383182,
    "VarianceExplained": 0.0006316615
  },
  "dropped_276": {
    "CumulativeVarianceExplained": 0.9934646254,
    "Mask": "Edge",
    "Method": "EdgeRegressor",
    "Retained": false,
    "SingularValue": 39.0195511006,
    "VarianceExplained": 0.0006221072
  },
  "dropped_277": {
    "CumulativeVarianceExplained": 0.9940831329,
    "Mask": "Edge",
    "Method": "EdgeRegressor",
    "Retained": false,
    "SingularValue": 38.9064960133,
    "VarianceExplained": 0.0006185075
  },
  "dropped_278": {
    "CumulativeVarianceExplained": 0.9946972279,
    "Mask": "Edge",
    "Method": "EdgeRegressor",
    "Retained": false,
    "SingularValue": 38.7674666706,
    "VarianceExplained": 0.000614095
  },
  "dropped_279": {
    "CumulativeVarianceExplained": 0.9953108329,
    "Mask": "Edge",
    "Method": "EdgeRegressor",
    "Retained": false,
    "SingularValue": 38.751995178,
    "VarianceExplained": 0.000613605
  },
  "dropped_28": {
    "CumulativeVarianceExplained": 0.7252762807,
    "Mask": "Edge",
    "Method": "EdgeRegressor",
    "Retained": false,
    "SingularValue": 67.7654591767,
    "VarianceExplained": 0.0018763657
  },
  "dropped_280": {
    "CumulativeVarianceExplained": 0.995922826,
    "Mask": "Edge",
    "Method": "EdgeRegressor",
    "Retained": false,
    "SingularValue": 38.7010660039,
    "VarianceExplained": 0.0006119932
  },
  "dropped_281": {
    "CumulativeVarianceExplained": 0.9965235159,
    "Mask": "Edge",
    "Method": "EdgeRegressor",
    "Retained": false,
    "SingularValue": 38.3420026788,
    "VarianceExplained": 0.0006006899
  },
  "dropped_282": {
    "CumulativeVarianceExplained": 0.9971201842,
    "Mask": "Edge",
    "Method": "EdgeRegressor",
    "Retained": false,
    "SingularValue": 38.2134374175,
    "VarianceExplained": 0.0005966683
  },
  "dropped_283": {
    "CumulativeVarianceExplained": 0.9977104613,
    "Mask": "Edge",
    "Method": "EdgeRegressor",
    "Retained": false,
    "SingularValue": 38.0082272902,
    "VarianceExplained": 0.0005902771
  },
  "dropped_284": {
    "CumulativeVarianceExplained": 0.9982951558,
    "Mask": "Edge",
    "Method": "EdgeRegressor",
    "Retained": false,
    "SingularValue": 37.8280667741,
    "VarianceExplained": 0.0005846945
  },
  "dropped_285": {
    "CumulativeVarianceExplained": 0.9988709883,
    "Mask": "Edge",
    "Method": "EdgeRegressor",
    "Retained": false,
    "SingularValue": 37.5402985005,
    "VarianceExplained": 0.0005758325
  },
  "dropped_286": {
    "CumulativeVarianceExplained": 0.9994439324,
    "Mask": "Edge",
    "Method": "EdgeRegressor",
    "Retained": false,
    "SingularValue": 37.4460283199,
    "VarianceExplained": 0.0005729441
  },
  "dropped_287": {
    "CumulativeVarianceExplained": 1.0,
    "Mask": "Edge",
    "Method": "EdgeRegressor",
    "Retained": false,
    "SingularValue": 36.8904064859,
    "VarianceExplained": 0.0005560676
  },
  "dropped_288": {
    "CumulativeVarianceExplained": 1.0,
    "Mask": "Edge",
    "Method": "EdgeRegressor",
    "Retained": false,
    "SingularValue": 0.0,
    "VarianceExplained": 0.0
  },
  "dropped_289": {
    "CumulativeVarianceExplained": 1.0,
    "Mask": "Edge",
    "Method": "EdgeRegressor",
    "Retained": false,
    "SingularValue": 0.0,
    "VarianceExplained": 0.0
  },
  "dropped_29": {
    "CumulativeVarianceExplained": 0.7271284153,
    "Mask": "Edge",
    "Method": "EdgeRegressor",
    "Retained": false,
    "SingularValue": 67.3264792285,
    "VarianceExplained": 0.0018521345
  },
  "dropped_290": {
    "CumulativeVarianceExplained": 1.0,
    "Mask": "Edge",
    "Method": "EdgeRegressor",
    "Retained": false,
    "SingularValue": 0.0,
    "VarianceExplained": 0.0
  },
  "dropped_291": {
    "CumulativeVarianceExplained": 1.0,
    "Mask": "Edge",
    "Method": "EdgeRegressor",
    "Retained": false,
    "SingularValue": 0.0,
    "VarianceExplained": 0.0
  },
  "dropped_292": {
    "CumulativeVarianceExplained": 1.0,
    "Mask": "Edge",
    "Method": "EdgeRegressor",
    "Retained": false,
    "SingularValue": 0.0,
    "VarianceExplained": 0.0
  },
  "dropped_293": {
    "CumulativeVarianceExplained": 1.0,
    "Mask": "Edge",
    "Method": "EdgeRegressor",
    "Retained": false,
    "SingularValue": 0.0,
    "VarianceExplained": 0.0
  },
  "dropped_294": {
    "CumulativeVarianceExplained": 1.0,
    "Mask": "Edge",
    "Method": "EdgeRegressor",
    "Retained": false,
    "SingularValue": 0.0,
    "VarianceExplained": 0.0
  },
  "dropped_3": {
    "CumulativeVarianceExplained": 0.6657576495,
    "Mask": "Edge",
    "Method": "EdgeRegressor",
    "Retained": false,
    "SingularValue": 91.2714069458,
    "VarianceExplained": 0.0034038484
  },
  "dropped_30": {
    "CumulativeVarianceExplained": 0.7289673057,
    "Mask": "Edge",
    "Method": "EdgeRegressor",
    "Retained": false,
    "SingularValue": 67.0853317088,
    "VarianceExplained": 0.0018388905
  },
  "dropped_31": {
    "CumulativeVarianceExplained": 0.7307466843,
    "Mask": "Edge",
    "Method": "EdgeRegressor",
    "Retained": false,
    "SingularValue": 65.9908639167,
    "VarianceExplained": 0.0017793785
  },
  "dropped_32": {
    "CumulativeVarianceExplained": 0.7325193546,
    "Mask": "Edge",
    "Method": "EdgeRegressor",
    "Retained": false,
    "SingularValue": 65.8663546384,
    "VarianceExplained": 0.0017726703
  },
  "dropped_33": {
    "CumulativeVarianceExplained": 0.7342793151,
    "Mask": "Edge",
    "Method": "EdgeRegressor",
    "Retained": false,
    "SingularValue": 65.6298024603,
    "VarianceExplained": 0.0017599605
  },
  "dropped_34": {
    "CumulativeVarianceExplained": 0.7360303266,
    "Mask": "Edge",
    "Method": "EdgeRegressor",
    "Retained": false,
    "SingularValue": 65.4627335182,
    "VarianceExplained": 0.0017510115
  },
  "dropped_35": {
    "CumulativeVarianceExplained": 0.7377632709,
    "Mask": "Edge",
    "Method": "EdgeRegressor",
    "Retained": false,
    "SingularValue": 65.1241307223,
    "VarianceExplained": 0.0017329443
  },
  "dropped_36": {
    "CumulativeVarianceExplained": 0.739485552,
    "Mask": "Edge",
    "Method": "EdgeRegressor",
    "Retained": false,
    "SingularValue": 64.9234602569,
    "VarianceExplained": 0.0017222811
  },
  "dropped_37": {
    "CumulativeVarianceExplained": 0.7411818777,
    "Mask": "Edge",
    "Method": "EdgeRegressor",
    "Retained": false,
    "SingularValue": 64.4323928372,
    "VarianceExplained": 0.0016963257
  },
  "dropped_38": {
    "CumulativeVarianceExplained": 0.7428642601,
    "Mask": "Edge",
    "Method": "EdgeRegressor",
    "Retained": false,
    "SingularValue": 64.1670391203,
    "VarianceExplained": 0.0016823824
  },
  "dropped_39": {
    "CumulativeVarianceExplained": 0.7445410727,
    "Mask": "Edge",
    "Method": "EdgeRegressor",
    "Retained": false,
    "SingularValue": 64.0607327942,
    "VarianceExplained": 0.0016768126
  },
  "dropped_4": {
    "CumulativeVarianceExplained": 0.669090096,
    "Mask": "Edge",
    "Method": "EdgeRegressor",
    "Retained": false,
    "SingularValue": 90.3090404476,
    "VarianceExplained": 0.0033324464
  },
  "dropped_40": {
    "CumulativeVarianceExplained": 0.7461981687,
    "Mask": "Edge",
    "Method": "EdgeRegressor",
    "Retained": false,
    "SingularValue": 63.6829940541,
    "VarianceExplained": 0.001657096
  },
  "dropped_41": {
    "CumulativeVarianceExplained": 0.7478522279,
    "Mask": "Edge",
    "Method": "EdgeRegressor",
    "Retained": false,
    "SingularValue": 63.6246143474,
    "VarianceExplained": 0.0016540592
  },
  "dropped_42": {
    "CumulativeVarianceExplained": 0.7494785349,
    "Mask": "Edge",
    "Method": "EdgeRegressor",
    "Retained": false,
    "SingularValue": 63.0886011616,
    "VarianceExplained": 0.001626307
  },
  "dropped_43": {
    "CumulativeVarianceExplained": 0.7511019061,
    "Mask": "Edge",
    "Method": "EdgeRegressor",
    "Retained": false,
    "SingularValue": 63.03163289,
    "VarianceExplained": 0.0016233712
  },
  "dropped_44": {
    "CumulativeVarianceExplained": 0.7527021078,
    "Mask": "Edge",
    "Method": "EdgeRegressor",
    "Retained": false,
    "SingularValue": 62.5802072364,
    "VarianceExplained": 0.0016002017
  },
  "dropped_45": {
    "CumulativeVarianceExplained": 0.7542948536,
    "Mask": "Edge",
    "Method": "EdgeRegressor",
    "Retained": false,
    "SingularValue": 62.4342478341,
    "VarianceExplained": 0.0015927459
  },
  "dropped_46": {
    "CumulativeVarianceExplained": 0.7558746543,
    "Mask": "Edge",
    "Method": "EdgeRegressor",
    "Retained": false,
    "SingularValue": 62.1800089733,
    "VarianceExplained": 0.0015798006
  },
  "dropped_47": {
    "CumulativeVarianceExplained": 0.7574516463,
    "Mask": "Edge",
    "Method": "EdgeRegressor",
    "Retained": false,
    "SingularValue": 62.1247125366,
    "VarianceExplained": 0.0015769921
  },
  "dropped_48": {
    "CumulativeVarianceExplained": 0.7590186399,
    "Mask": "Edge",
    "Method": "EdgeRegressor",
    "Retained": false,
    "SingularValue": 61.9274557488,
    "VarianceExplained": 0.0015669935
  },
  "dropped_49": {
    "CumulativeVarianceExplained": 0.760583139,
    "Mask": "Edge",
    "Method": "EdgeRegressor",
    "Retained": false,
    "SingularValue": 61.8781475102,
    "VarianceExplained": 0.0015644991
  },
  "dropped_5": {
    "CumulativeVarianceExplained": 0.6722923134,
    "Mask": "Edge",
    "Method": "EdgeRegressor",
    "Retained": false,
    "SingularValue": 88.5268569761,
    "VarianceExplained": 0.0032022174
  },
  "dropped_50": {
    "CumulativeVarianceExplained": 0.7621287627,
    "Mask": "Edge",
    "Method": "EdgeRegressor",
    "Retained": false,
    "SingularValue": 61.503739499,
    "VarianceExplained": 0.0015456237
  },
  "dropped_51": {
    "CumulativeVarianceExplained": 0.7636597925,
    "Mask": "Edge",
    "Method": "EdgeRegressor",
    "Retained": false,
    "SingularValue": 61.2126887025,
    "VarianceExplained": 0.0015310298
  },
  "dropped_52": {
    "CumulativeVarianceExplained": 0.7651755568,
    "Mask": "Edge",
    "Method": "EdgeRegressor",
    "Retained": false,
    "SingularValue": 60.9067573441,
    "VarianceExplained": 0.0015157643
  },
  "dropped_53": {
    "CumulativeVarianceExplained": 0.766686577,
    "Mask": "Edge",
    "Method": "EdgeRegressor",
    "Retained": false,
    "SingularValue": 60.8113690095,
    "VarianceExplained": 0.0015110202
  },
  "dropped_54": {
    "CumulativeVarianceExplained": 0.7681895044,
    "Mask": "Edge",
    "Method": "EdgeRegressor",
    "Retained": false,
    "SingularValue": 60.6483015148,
    "VarianceExplained": 0.0015029274
  },
  "dropped_55": {
    "CumulativeVarianceExplained": 0.7696777001,
    "Mask": "Edge",
    "Method": "EdgeRegressor",
    "Retained": false,
    "SingularValue": 60.3503312192,
    "VarianceExplained": 0.0014881957
  },
  "dropped_56": {
    "CumulativeVarianceExplained": 0.7711633099,
    "Mask": "Edge",
    "Method": "EdgeRegressor",
    "Retained": false,
    "SingularValue": 60.2978752408,
    "VarianceExplained": 0.0014856097
  },
  "dropped_57": {
    "CumulativeVarianceExplained": 0.7726400718,
    "Mask": "Edge",
    "Method": "EdgeRegressor",
    "Retained": false,
    "SingularValue": 60.1180503057,
    "VarianceExplained": 0.001476762
  },
  "dropped_58": {
    "CumulativeVarianceExplained": 0.774105927,
    "Mask": "Edge",
    "Method": "EdgeRegressor",
    "Retained": false,
    "SingularValue": 59.8956341625,
    "VarianceExplained": 0.0014658552
  },
  "dropped_59": {
    "CumulativeVarianceExplained": 0.7755704584,
    "Mask": "Edge",
    "Method": "EdgeRegressor",
    "Retained": false,
    "SingularValue": 59.8685827294,
    "VarianceExplained": 0.0014645314
  },
  "dropped_6": {
    "CumulativeVarianceExplained": 0.6753866228,
    "Mask": "Edge",
    "Method": "EdgeRegressor",
    "Retained": false,
    "SingularValue": 87.0224901516,
    "VarianceExplained": 0.0030943094
  },
  "dropped_60": {
    "CumulativeVarianceExplained": 0.777028218,
    "Mask": "Edge",
    "Method": "EdgeRegressor",
    "Retained": false,
    "SingularValue": 59.7300123439,
    "VarianceExplained": 0.0014577597
  },
  "dropped_61": {
    "CumulativeVarianceExplained": 0.7784763653,
    "Mask": "Edge",
    "Method": "EdgeRegressor",
    "Retained": false,
    "SingularValue": 59.532757458,
    "VarianceExplained": 0.0014481472
  },
  "dropped_62": {
    "CumulativeVarianceExplained": 0.7799120377,
    "Mask": "Edge",
    "Method": "EdgeRegressor",
    "Retained": false,
    "SingularValue": 59.2757859512,
    "VarianceExplained": 0.0014356724
  },
  "dropped_63": {
    "CumulativeVarianceExplained": 0.7813436451,
    "Mask": "Edge",
    "Method": "EdgeRegressor",
    "Retained": false,
    "SingularValue": 59.1918083854,
    "VarianceExplained": 0.0014316074
  },
  "dropped_64": {
    "CumulativeVarianceExplained": 0.7827677902,
    "Mask": "Edge",
    "Method": "EdgeRegressor",
    "Retained": false,
    "SingularValue": 59.0373360175,
    "VarianceExplained": 0.0014241451
  },
  "dropped_65": {
    "CumulativeVarianceExplained": 0.7841862665,
    "Mask": "Edge",
    "Method": "EdgeRegressor",
    "Retained": false,
    "SingularValue": 58.9197210227,
    "VarianceExplained": 0.0014184763
  },
  "dropped_66": {
    "CumulativeVarianceExplained": 0.7855980036,
    "Mask": "Edge",
    "Method": "EdgeRegressor",
    "Retained": false,
    "SingularValue": 58.7795899125,
    "VarianceExplained": 0.0014117371
  },
  "dropped_67": {
    "CumulativeVarianceExplained": 0.7870031849,
    "Mask": "Edge",
    "Method": "EdgeRegressor",
    "Retained": false,
    "SingularValue": 58.6429518729,
    "VarianceExplained": 0.0014051813
  },
  "dropped_68": {
    "CumulativeVarianceExplained": 0.7884055533,
    "Mask": "Edge",
    "Method": "EdgeRegressor",
    "Retained": false,
    "SingularValue": 58.584226486,
    "VarianceExplained": 0.0014023684
  },
  "dropped_69": {
    "CumulativeVarianceExplained": 0.7898021677,
    "Mask": "Edge",
    "Method": "EdgeRegressor",
    "Retained": false,
    "SingularValue": 58.4639141036,
    "VarianceExplained": 0.0013966143
  },
  "dropped_7": {
    "CumulativeVarianceExplained": 0.6783441556,
    "Mask": "Edge",
    "Method": "EdgeRegressor",
    "Retained": false,
    "SingularValue": 85.077442248,
    "VarianceExplained": 0.0029575328
  },
  "dropped_70": {
    "CumulativeVarianceExplained": 0.7911894017,
    "Mask": "Edge",
    "Method": "EdgeRegressor",
    "Retained": false,
    "SingularValue": 58.2672484225,
    "VarianceExplained": 0.0013872341
  },
  "dropped_71": {
    "CumulativeVarianceExplained": 0.7925737604,
    "Mask": "Edge",
    "Method": "EdgeRegressor",
    "Retained": false,
    "SingularValue": 58.2068295485,
    "VarianceExplained": 0.0013843586
  },
  "dropped_72": {
    "CumulativeVarianceExplained": 0.7939503892,
    "Mask": "Edge",
    "Method": "EdgeRegressor",
    "Retained": false,
    "SingularValue": 58.0440993009,
    "VarianceExplained": 0.0013766289
  },
  "dropped_73": {
    "CumulativeVarianceExplained": 0.795320978,
    "Mask": "Edge",
    "Method": "EdgeRegressor",
    "Retained": false,
    "SingularValue": 57.9166219636,
    "VarianceExplained": 0.0013705888
  },
  "dropped_74": {
    "CumulativeVarianceExplained": 0.796685665,
    "Mask": "Edge",
    "Method": "EdgeRegressor",
    "Retained": false,
    "SingularValue": 57.7917923526,
    "VarianceExplained": 0.001364687
  },
  "dropped_75": {
    "CumulativeVarianceExplained": 0.7980485161,
    "Mask": "Edge",
    "Method": "EdgeRegressor",
    "Retained": false,
    "SingularValue": 57.7529060637,
    "VarianceExplained": 0.0013628511
  },
  "dropped_76": {
    "CumulativeVarianceExplained": 0.7994075776,
    "Mask": "Edge",
    "Method": "EdgeRegressor",
    "Retained": false,
    "SingularValue": 57.6725559973,
    "VarianceExplained": 0.0013590615
  },
  "dropped_77": {
    "CumulativeVarianceExplained": 0.8007605593,
    "Mask": "Edge",
    "Method": "EdgeRegressor",
    "Retained": false,
    "SingularValue": 57.5434110524,
    "VarianceExplained": 0.0013529817
  },
  "dropped_78": {
    "CumulativeVarianceExplained": 0.802104325,
    "Mask": "Edge",
    "Method": "EdgeRegressor",
    "Retained": false,
    "SingularValue": 57.3470934489,
    "VarianceExplained": 0.0013437657
  },
  "dropped_79": {
    "CumulativeVarianceExplained": 0.8034401725,
    "Mask": "Edge",
    "Method": "EdgeRegressor",
    "Retained": false,
    "SingularValue": 57.177884056,
    "VarianceExplained": 0.0013358475
  },
  "dropped_8": {
    "CumulativeVarianceExplained": 0.6811358462,
    "Mask": "Edge",
    "Method": "EdgeRegressor",
    "Retained": false,
    "SingularValue": 82.6576933062,
    "VarianceExplained": 0.0027916906
  },
  "dropped_80": {
    "CumulativeVarianceExplained": 0.8047720078,
    "Mask": "Edge",
    "Method": "EdgeRegressor",
    "Retained": false,
    "SingularValue": 57.0919521615,
    "VarianceExplained": 0.0013318353
  },
  "dropped_81": {
    "CumulativeVarianceExplained": 0.8060933303,
    "Mask": "Edge",
    "Method": "EdgeRegressor",
    "Retained": false,
    "SingularValue": 56.8661795564,
    "VarianceExplained": 0.0013213225
  },
  "dropped_82": {
    "CumulativeVarianceExplained": 0.8074124964,
    "Mask": "Edge",
    "Method": "EdgeRegressor",
    "Retained": false,
    "SingularValue": 56.8197594805,
    "VarianceExplained": 0.0013191662
  },
  "dropped_83": {
    "CumulativeVarianceExplained": 0.8087294606,
    "Mask": "Edge",
    "Method": "EdgeRegressor",
    "Retained": false,
    "SingularValue": 56.7723159358,
    "VarianceExplained": 0.0013169641
  },
  "dropped_84": {
    "CumulativeVarianceExplained": 0.8100408118,
    "Mask": "Edge",
    "Method": "EdgeRegressor",
    "Retained": false,
    "SingularValue": 56.6512060042,
    "VarianceExplained": 0.0013113513
  },
  "dropped_85": {
    "CumulativeVarianceExplained": 0.8113502105,
    "Mask": "Edge",
    "Method": "EdgeRegressor",
    "Retained": false,
    "SingularValue": 56.6090133106,
    "VarianceExplained": 0.0013093987
  },
  "dropped_86": {
    "CumulativeVarianceExplained": 0.8126571011,
    "Mask": "Edge",
    "Method": "EdgeRegressor",
    "Retained": false,
    "SingularValue": 56.5547709608,
    "VarianceExplained": 0.0013068906
  },
  "dropped_87": {
    "CumulativeVarianceExplained": 0.8139610336,
    "Mask": "Edge",
    "Method": "EdgeRegressor",
    "Retained": false,
    "SingularValue": 56.4907312456,
    "VarianceExplained": 0.0013039325
  },
  "dropped_88": {
    "CumulativeVarianceExplained": 0.8152618474,
    "Mask": "Edge",
    "Method": "EdgeRegressor",
    "Retained": false,
    "SingularValue": 56.4231350426,
    "VarianceExplained": 0.0013008138
  },
  "dropped_89": {
    "CumulativeVarianceExplained": 0.8165596415,
    "Mask": "Edge",
    "Method": "EdgeRegressor",
    "Retained": false,
    "SingularValue": 56.3576050473,
    "VarianceExplained": 0.0012977941
  },
  "dropped_9": {
    "CumulativeVarianceExplained": 0.6838756759,
    "Mask": "Edge",
    "Method": "EdgeRegressor",
    "Retained": false,
    "SingularValue": 81.8863332384,
    "VarianceExplained": 0.0027398297
  },
  "dropped_90": {
    "CumulativeVarianceExplained": 0.8178475096,
    "Mask": "Edge",
    "Method": "EdgeRegressor",
    "Retained": false,
    "SingularValue": 56.1416709025,
    "VarianceExplained": 0.0012878681
  },
  "dropped_91": {
    "CumulativeVarianceExplained": 0.8191251113,
    "Mask": "Edge",
    "Method": "EdgeRegressor",
    "Retained": false,
    "SingularValue": 55.9174519763,
    "VarianceExplained": 0.0012776017
  },
  "dropped_92": {
    "CumulativeVarianceExplained": 0.8204003484,
    "Mask": "Edge",
    "Method": "EdgeRegressor",
    "Retained": false,
    "SingularValue": 55.8656827587,
    "VarianceExplained": 0.0012752371
  },
  "dropped_93": {
    "CumulativeVarianceExplained": 0.8216734549,
    "Mask": "Edge",
    "Method": "EdgeRegressor",
    "Retained": false,
    "SingularValue": 55.8189951308,
    "VarianceExplained": 0.0012731065
  },
  "dropped_94": {
    "CumulativeVarianceExplained": 0.822944962,
    "Mask": "Edge",
    "Method": "EdgeRegressor",
    "Retained": false,
    "SingularValue": 55.7839205867,
    "VarianceExplained": 0.0012715071
  },
  "dropped_95": {
    "CumulativeVarianceExplained": 0.8242133989,
    "Mask": "Edge",
    "Method": "EdgeRegressor",
    "Retained": false,
    "SingularValue": 55.7165304669,
    "VarianceExplained": 0.0012684369
  },
  "dropped_96": {
    "CumulativeVarianceExplained": 0.8254768516,
    "Mask": "Edge",
    "Method": "EdgeRegressor",
    "Retained": false,
    "SingularValue": 55.606958676,
    "VarianceExplained": 0.0012634528
  },
  "dropped_97": {
    "CumulativeVarianceExplained": 0.8267348111,
    "Mask": "Edge",
    "Method": "EdgeRegressor",
    "Retained": false,
    "SingularValue": 55.4859426178,
    "VarianceExplained": 0.0012579595
  },
  "dropped_98": {
    "CumulativeVarianceExplained": 0.8279861163,
    "Mask": "Edge",
    "Method": "EdgeRegressor",
    "Retained": false,
    "SingularValue": 55.3389942213,
    "VarianceExplained": 0.0012513052
  },
  "dropped_99": {
    "CumulativeVarianceExplained": 0.8292348231,
    "Mask": "Edge",
    "Method": "EdgeRegressor",
    "Retained": false,
    "SingularValue": 55.2815078242,
    "VarianceExplained": 0.0012487068
  },
  "edge_comp_00": {
    "CumulativeVarianceExplained": 0.2261039166,
    "Mask": "Edge",
    "Method": "EdgeRegressor",
    "Retained": true,
    "SingularValue": 743.881368378,
    "VarianceExplained": 0.2261039166
  },
  "edge_comp_01": {
    "CumulativeVarianceExplained": 0.3169328314,
    "Mask": "Edge",
    "Method": "EdgeRegressor",
    "Retained": true,
    "SingularValue": 471.4782916126,
    "VarianceExplained": 0.0908289148
  },
  "edge_comp_02": {
    "CumulativeVarianceExplained": 0.3875263615,
    "Mask": "Edge",
    "Method": "EdgeRegressor",
    "Retained": true,
    "SingularValue": 415.6541189504,
    "VarianceExplained": 0.0705935301
  },
  "edge_comp_03": {
    "CumulativeVarianceExplained": 0.425807623,
    "Mask": "Edge",
    "Method": "EdgeRegressor",
    "Retained": true,
    "SingularValue": 306.0855016543,
    "VarianceExplained": 0.0382812615
  },
  "edge_comp_04": {
    "CumulativeVarianceExplained": 0.4586721149,
    "Mask": "Edge",
    "Method": "EdgeRegressor",
    "Retained": true,
    "SingularValue": 283.6044884763,
    "VarianceExplained": 0.0328644919
  },
  "edge_comp_05": {
    "CumulativeVarianceExplained": 0.4867502153,
    "Mask": "Edge",
    "Method": "EdgeRegressor",
    "Retained": true,
    "SingularValue": 262.1401238116,
    "VarianceExplained": 0.0280781004
  },
  "edge_comp_06": {
    "CumulativeVarianceExplained": 0.5093042067,
    "Mask": "Edge",
    "Method": "EdgeRegressor",
    "Retained": true,
    "SingularValue": 234.9423689945,
    "VarianceExplained": 0.0225539914
  },
  "edge_comp_07": {
    "CumulativeVarianceExplained": 0.5273075306,
    "Mask": "Edge",
    "Method": "EdgeRegressor",
    "Retained": true,
    "SingularValue": 209.9065478356,
    "VarianceExplained": 0.0180033239
  },
  "edge_comp_08": {
    "CumulativeVarianceExplained": 0.5427477033,
    "Mask": "Edge",
    "Method": "EdgeRegressor",
    "Retained": true,
    "SingularValue": 194.3908037702,
    "VarianceExplained": 0.0154401727
  },
  "edge_comp_09": {
    "CumulativeVarianceExplained": 0.5578808268,
    "Mask": "Edge",
    "Method": "EdgeRegressor",
    "Retained": true,
    "SingularValue": 192.4482321655,
    "VarianceExplained": 0.0151331234
  },
  "edge_comp_10": {
    "CumulativeVarianceExplained": 0.5712257998,
    "Mask": "Edge",
    "Method": "EdgeRegressor",
    "Retained": true,
    "SingularValue": 180.7209449771,
    "VarianceExplained": 0.013344973
  },
  "edge_comp_11": {
    "CumulativeVarianceExplained": 0.5815997486,
    "Mask": "Edge",
    "Method": "EdgeRegressor",
    "Retained": true,
    "SingularValue": 159.3388541189,
    "VarianceExplained": 0.0103739488
  },
  "edge_comp_12": {
    "CumulativeVarianceExplained": 0.5913444182,
    "Mask": "Edge",
    "Method": "EdgeRegressor",
    "Retained": true,
    "SingularValue": 154.4305423181,
    "VarianceExplained": 0.0097446695
  },
  "edge_comp_13": {
    "CumulativeVarianceExplained": 0.5995241191,
    "Mask": "Edge",
    "Method": "EdgeRegressor",
    "Retained": true,
    "SingularValue": 141.4875909865,
    "VarianceExplained": 0.008179701
  },
  "edge_comp_14": {
    "CumulativeVarianceExplained": 0.6066587941,
    "Mask": "Edge",
    "Method": "EdgeRegressor",
    "Retained": true,
    "SingularValue": 132.1407397339,
    "VarianceExplained": 0.0071346749
  },
  "edge_comp_15": {
    "CumulativeVarianceExplained": 0.6131817751,
    "Mask": "Edge",
    "Method": "EdgeRegressor",
    "Retained": true,
    "SingularValue": 126.3492581861,
    "VarianceExplained": 0.006522981
  },
  "edge_comp_16": {
    "CumulativeVarianceExplained": 0.6191456787,
    "Mask": "Edge",
    "Method": "EdgeRegressor",
    "Retained": true,
    "SingularValue": 120.8133550427,
    "VarianceExplained": 0.0059639036
  },
  "edge_comp_17": {
    "CumulativeVarianceExplained": 0.624690171,
    "Mask": "Edge",
    "Method": "EdgeRegressor",
    "Retained": true,
    "SingularValue": 116.4878238905,
    "VarianceExplained": 0.0055444923
  },
  "edge_comp_18": {
    "CumulativeVarianceExplained": 0.6296556622,
    "Mask": "Edge",
    "Method": "EdgeRegressor",
    "Retained": true,
    "SingularValue": 110.2378528701,
    "VarianceExplained": 0.0049654912
  },
  "edge_comp_19": {
    "CumulativeVarianceExplained": 0.6341754364,
    "Mask": "Edge",
    "Method": "EdgeRegressor",
    "Retained": true,
    "SingularValue": 105.1739079559,
    "VarianceExplained": 0.0045197743
  },
  "edge_comp_20": {
    "CumulativeVarianceExplained": 0.6386633826,
    "Mask": "Edge",
    "Method": "EdgeRegressor",
    "Retained": true,
    "SingularValue": 104.8029374289,
    "VarianceExplained": 0.0044879461
  },
  "edge_comp_21": {
    "CumulativeVarianceExplained": 0.643062115,
    "Mask": "Edge",
    "Method": "EdgeRegressor",
    "Retained": true,
    "SingularValue": 103.7560457392,
    "VarianceExplained": 0.0043987324
  },
  "edge_comp_22": {
    "CumulativeVarianceExplained": 0.6471540265,
    "Mask": "Edge",
    "Method": "EdgeRegressor",
    "Retained": true,
    "SingularValue": 100.0720400623,
    "VarianceExplained": 0.0040919115
  },
  "edge_comp_23": {
    "CumulativeVarianceExplained": 0.6512105457,
    "Mask": "Edge",
    "Method": "EdgeRegressor",
    "Retained": true,
    "SingularValue": 99.6383225891,
    "VarianceExplained": 0.0040565192
  },
  "framewise_displacement": {
    "Units": "mm"
  },
  "rot_x": {
    "Description": "Rotation about left-right axis. Also known as \"pitch\".",
    "Units": "rad"
  },
  "rot_y": {
    "Description": "Rotation about anterior-posterior axis. Also known as \"roll\".",
    "Units": "rad"
  },
  "rot_z": {
    "Description": "Rotation about superior-inferior axis. Also known as \"yaw\".",
    "Units": "rad"
  },
  "t_comp_cor_00": {
    "CumulativeVarianceExplained": 0.6663530461,
    "Method": "tCompCor",
    "Retained": true,
    "SingularValue": 355.6362466239,
    "VarianceExplained": 0.6663530461
  },
  "trans_x": {
    "Description": "Translation along left-right axis.",
    "Units": "mm"
  },
  "trans_y": {
    "Description": "Translation along anterior-posterior axis.",
    "Units": "mm"
  },
  "trans_z": {
    "Description": "Translation along superior-inferior axis.",
    "Units": "mm"
  },
  "w_comp_cor_00": {
    "CumulativeVarianceExplained": 0.0897906123,
    "Mask": "WM",
    "Method": "aCompCor",
    "Retained": true,
    "SingularValue": 143.3079838184,
    "VarianceExplained": 0.0897906123
  },
  "w_comp_cor_01": {
    "CumulativeVarianceExplained": 0.1291007757,
    "Mask": "WM",
    "Method": "aCompCor",
    "Retained": true,
    "SingularValue": 94.8216140528,
    "VarianceExplained": 0.0393101633
  },
  "w_comp_cor_02": {
    "CumulativeVarianceExplained": 0.161734052,
    "Mask": "WM",
    "Method": "aCompCor",
    "Retained": true,
    "SingularValue": 86.3943334533,
    "VarianceExplained": 0.0326332763
  },
  "w_comp_cor_03": {
    "CumulativeVarianceExplained": 0.1812262946,
    "Mask": "WM",
    "Method": "aCompCor",
    "Retained": true,
    "SingularValue": 66.7706837144,
    "VarianceExplained": 0.0194922426
  },
  "w_comp_cor_04": {
    "CumulativeVarianceExplained": 0.1989895229,
    "Mask": "WM",
    "Method": "aCompCor",
    "Retained": true,
    "SingularValue": 63.7405591652,
    "VarianceExplained": 0.0177632284
  },
  "w_comp_cor_05": {
    "CumulativeVarianceExplained": 0.2150601623,
    "Mask": "WM",
    "Method": "aCompCor",
    "Retained": true,
    "SingularValue": 60.6277563498,
    "VarianceExplained": 0.0160706393
  },
  "w_comp_cor_06": {
    "CumulativeVarianceExplained": 0.2288189901,
    "Mask": "WM",
    "Method": "aCompCor",
    "Retained": true,
    "SingularValue": 56.0977750758,
    "VarianceExplained": 0.0137588278
  },
  "w_comp_cor_07": {
    "CumulativeVarianceExplained": 0.2407725043,
    "Mask": "WM",
    "Method": "aCompCor",
    "Retained": true,
    "SingularValue": 52.2880831046,
    "VarianceExplained": 0.0119535142
  },
  "w_comp_cor_08": {
    "CumulativeVarianceExplained": 0.2518337489,
    "Mask": "WM",
    "Method": "aCompCor",
    "Retained": true,
    "SingularValue": 50.2987180748,
    "VarianceExplained": 0.0110612446
  },
  "w_comp_cor_09": {
    "CumulativeVarianceExplained": 0.2617187124,
    "Mask": "WM",
    "Method": "aCompCor",
    "Retained": true,
    "SingularValue": 47.5491169081,
    "VarianceExplained": 0.0098849636
  },
  "w_comp_cor_10": {
    "CumulativeVarianceExplained": 0.2704974976,
    "Mask": "WM",
    "Method": "aCompCor",
    "Retained": true,
    "SingularValue": 44.809709637,
    "VarianceExplained": 0.0087787852
  },
  "w_comp_cor_11": {
    "CumulativeVarianceExplained": 0.278879467,
    "Mask": "WM",
    "Method": "aCompCor",
    "Retained": true,
    "SingularValue": 43.7852623769,
    "VarianceExplained": 0.0083819695
  },
  "w_comp_cor_12": {
    "CumulativeVarianceExplained": 0.286856089,
    "Mask": "WM",
    "Method": "aCompCor",
    "Retained": true,
    "SingularValue": 42.7134278316,
    "VarianceExplained": 0.007976622
  },
  "w_comp_cor_13": {
    "CumulativeVarianceExplained": 0.2944788832,
    "Mask": "WM",
    "Method": "aCompCor",
    "Retained": true,
    "SingularValue": 41.7553392482,
    "VarianceExplained": 0.0076227942
  },
  "w_comp_cor_14": {
    "CumulativeVarianceExplained": 0.3017683234,
    "Mask": "WM",
    "Method": "aCompCor",
    "Retained": true,
    "SingularValue": 40.8321272323,
    "VarianceExplained": 0.0072894401
  },
  "w_comp_cor_15": {
    "CumulativeVarianceExplained": 0.3087672412,
    "Mask": "WM",
    "Method": "aCompCor",
    "Retained": true,
    "SingularValue": 40.0101672562,
    "VarianceExplained": 0.0069989178
  },
  "w_comp_cor_16": {
    "CumulativeVarianceExplained": 0.3156136389,
    "Mask": "WM",
    "Method": "aCompCor",
    "Retained": true,
    "SingularValue": 39.5718158632,
    "VarianceExplained": 0.0068463977
  },
  "w_comp_cor_17": {
    "CumulativeVarianceExplained": 0.3222524349,
    "Mask": "WM",
    "Method": "aCompCor",
    "Retained": true,
    "SingularValue": 38.9672341748,
    "VarianceExplained": 0.006638796
  },
  "w_comp_cor_18": {
    "CumulativeVarianceExplained": 0.3288608604,
    "Mask": "WM",
    "Method": "aCompCor",
    "Retained": true,
    "SingularValue": 38.8780003122,
    "VarianceExplained": 0.0066084255
  },
  "w_comp_cor_19": {
    "CumulativeVarianceExplained": 0.3353245967,
    "Mask": "WM",
    "Method": "aCompCor",
    "Retained": true,
    "SingularValue": 38.4500346756,
    "VarianceExplained": 0.0064637363
  },
  "w_comp_cor_20": {
    "CumulativeVarianceExplained": 0.3415785308,
    "Mask": "WM",
    "Method": "aCompCor",
    "Retained": true,
    "SingularValue": 37.8208746927,
    "VarianceExplained": 0.0062539341
  },
  "w_comp_cor_21": {
    "CumulativeVarianceExplained": 0.3477889903,
    "Mask": "WM",
    "Method": "aCompCor",
    "Retained": true,
    "SingularValue": 37.6891886363,
    "VarianceExplained": 0.0062104596
  },
  "w_comp_cor_22": {
    "CumulativeVarianceExplained": 0.3539503196,
    "Mask": "WM",
    "Method": "aCompCor",
    "Retained": true,
    "SingularValue": 37.5398149725,
    "VarianceExplained": 0.0061613292
  },
  "w_comp_cor_23": {
    "CumulativeVarianceExplained": 0.3600509403,
    "Mask": "WM",
    "Method": "aCompCor",
    "Retained": true,
    "SingularValue": 37.3544143901,
    "VarianceExplained": 0.0061006207
  },
  "w_comp_cor_24": {
    "CumulativeVarianceExplained": 0.3660721034,
    "Mask": "WM",
    "Method": "aCompCor",
    "Retained": true,
    "SingularValue": 37.1103554506,
    "VarianceExplained": 0.0060211631
  },
  "w_comp_cor_25": {
    "CumulativeVarianceExplained": 0.3719955834,
    "Mask": "WM",
    "Method": "aCompCor",
    "Retained": true,
    "SingularValue": 36.8080985715,
    "VarianceExplained": 0.00592348
  },
  "w_comp_cor_26": {
    "CumulativeVarianceExplained": 0.3777748008,
    "Mask": "WM",
    "Method": "aCompCor",
    "Retained": true,
    "SingularValue": 36.357116959,
    "VarianceExplained": 0.0057792175
  },
  "w_comp_cor_27": {
    "CumulativeVarianceExplained": 0.3834956318,
    "Mask": "WM",
    "Method": "aCompCor",
    "Retained": true,
    "SingularValue": 36.1729957733,
    "VarianceExplained": 0.005720831
  },
  "w_comp_cor_28": {
    "CumulativeVarianceExplained": 0.3891687254,
    "Mask": "WM",
    "Method": "aCompCor",
    "Retained": true,
    "SingularValue": 36.0217570691,
    "VarianceExplained": 0.0056730936
  },
  "w_comp_cor_29": {
    "CumulativeVarianceExplained": 0.3947737276,
    "Mask": "WM",
    "Method": "aCompCor",
    "Retained": true,
    "SingularValue": 35.8049286219,
    "VarianceExplained": 0.0056050022
  },
  "w_comp_cor_30": {
    "CumulativeVarianceExplained": 0.4003485565,
    "Mask": "WM",
    "Method": "aCompCor",
    "Retained": true,
    "SingularValue": 35.7084248456,
    "VarianceExplained": 0.005574829
  },
  "w_comp_cor_31": {
    "CumulativeVarianceExplained": 0.4058352332,
    "Mask": "WM",
    "Method": "aCompCor",
    "Retained": true,
    "SingularValue": 35.4249791741,
    "VarianceExplained": 0.0054866767
  },
  "w_comp_cor_32": {
    "CumulativeVarianceExplained": 0.4112667807,
    "Mask": "WM",
    "Method": "aCompCor",
    "Retained": true,
    "SingularValue": 35.2465578247,
    "VarianceExplained": 0.0054315475
  },
  "w_comp_cor_33": {
    "CumulativeVarianceExplained": 0.4166828222,
    "Mask": "WM",
    "Method": "aCompCor",
    "Retained": true,
    "SingularValue": 35.1962109693,
    "VarianceExplained": 0.0054160415
  },
  "w_comp_cor_34": {
    "CumulativeVarianceExplained": 0.422013148,
    "Mask": "WM",
    "Method": "aCompCor",
    "Retained": true,
    "SingularValue": 34.9165877554,
    "VarianceExplained": 0.0053303258
  },
  "w_comp_cor_35": {
    "CumulativeVarianceExplained": 0.4273057163,
    "Mask": "WM",
    "Method": "aCompCor",
    "Retained": true,
    "SingularValue": 34.7927016,
    "VarianceExplained": 0.0052925682
  },
  "w_comp_cor_36": {
    "CumulativeVarianceExplained": 0.4325676647,
    "Mask": "WM",
    "Method": "aCompCor",
    "Retained": true,
    "SingularValue": 34.6919103689,
    "VarianceExplained": 0.0052619485
  },
  "w_comp_cor_37": {
    "CumulativeVarianceExplained": 0.4378013476,
    "Mask": "WM",
    "Method": "aCompCor",
    "Retained": true,
    "SingularValue": 34.5986076558,
    "VarianceExplained": 0.0052336829
  },
  "w_comp_cor_38": {
    "CumulativeVarianceExplained": 0.4429440642,
    "Mask": "WM",
    "Method": "aCompCor",
    "Retained": true,
    "SingularValue": 34.2966113881,
    "VarianceExplained": 0.0051427165
  },
  "w_comp_cor_39": {
    "CumulativeVarianceExplained": 0.4480618015,
    "Mask": "WM",
    "Method": "aCompCor",
    "Retained": true,
    "SingularValue": 34.2132172277,
    "VarianceExplained": 0.0051177373
  },
  "w_comp_cor_40": {
    "CumulativeVarianceExplained": 0.4531151187,
    "Mask": "WM",
    "Method": "aCompCor",
    "Retained": true,
    "SingularValue": 33.9972039531,
    "VarianceExplained": 0.0050533172
  },
  "w_comp_cor_41": {
    "CumulativeVarianceExplained": 0.4581615018,
    "Mask": "WM",
    "Method": "aCompCor",
    "Retained": true,
    "SingularValue": 33.9738705437,
    "VarianceExplained": 0.0050463831
  },
  "w_comp_cor_42": {
    "CumulativeVarianceExplained": 0.46312092,
    "Mask": "WM",
    "Method": "aCompCor",
    "Retained": true,
    "SingularValue": 33.6798606637,
    "VarianceExplained": 0.0049594182
  },
  "w_comp_cor_43": {
    "CumulativeVarianceExplained": 0.4680442647,
    "Mask": "WM",
    "Method": "aCompCor",
    "Retained": true,
    "SingularValue": 33.5571477803,
    "VarianceExplained": 0.0049233447
  },
  "w_comp_cor_44": {
    "CumulativeVarianceExplained": 0.4729473526,
    "Mask": "WM",
    "Method": "aCompCor",
    "Retained": true,
    "SingularValue": 33.4880421395,
    "VarianceExplained": 0.0049030879
  },
  "w_comp_cor_45": {
    "CumulativeVarianceExplained": 0.4777977246,
    "Mask": "WM",
    "Method": "aCompCor",
    "Retained": true,
    "SingularValue": 33.3075312221,
    "VarianceExplained": 0.004850372
  },
  "w_comp_cor_46": {
    "CumulativeVarianceExplained": 0.482588981,
    "Mask": "WM",
    "Method": "aCompCor",
    "Retained": true,
    "SingularValue": 33.1039354304,
    "VarianceExplained": 0.0047912564
  },
  "w_comp_cor_47": {
    "CumulativeVarianceExplained": 0.4873578937,
    "Mask": "WM",
    "Method": "aCompCor",
    "Retained": true,
    "SingularValue": 33.026656063,
    "VarianceExplained": 0.0047689127
  },
  "w_comp_cor_48": {
    "CumulativeVarianceExplained": 0.4920970396,
    "Mask": "WM",
    "Method": "aCompCor",
    "Retained": true,
    "SingularValue": 32.9234213927,
    "VarianceExplained": 0.0047391459
  },
  "w_comp_cor_49": {
    "CumulativeVarianceExplained": 0.496824601,
    "Mask": "WM",
    "Method": "aCompCor",
    "Retained": true,
    "SingularValue": 32.8831571727,
    "VarianceExplained": 0.0047275614
  },
  "w_comp_cor_50": {
    "CumulativeVarianceExplained": 0.5015227759,
    "Mask": "WM",
    "Method": "aCompCor",
    "Retained": true,
    "SingularValue": 32.7807972124,
    "VarianceExplained": 0.0046981749
  }
}